Workbook

Sheet Lineas de Credito
A2: LINEAS DE CREDITOS VIGENTES
A4: N° | B4: Linea | C4: Descripción Producto | D4: Tasa | E4: Tipo_Cartera | F4: Desprotegido Max | H4: Credito Afianzado
A5: 1 | B5: 1023 | C5: Compra Cartera | D5: 0.01 | E5: Consumo | H5: SI
A6: 2 | B6: 1024 | C6: Cred. Ord. Ant. Cinco Años | H6: NO
A7: 3 | B7: 1025 | C7: Credito Empleados
A8: 4 | B8: 1026 | C8: Credito Ordinario
A9: 5 | B9: 1028 | C9: Cred. Ord. Ant. Quince Años
A10: 6 | B10: 1031 | C10: Ptmo.Ord.No24
A11: 7 | B11: 1032 | C11: Credito De Vehiculo
A12: 8 | B12: 1034 | C12: Ptmo.Ant.Prim
A13: 9 | B13: 1035 | C13: Educativo
A14: 10 | B14: 1037 | C14: Orden Comercio
A15: 11 | B15: 1042 | C15: Eventos
A16: 12 | B16: 1043 | C16: Cred. Ord. Ant. Diez Años
A17: 13 | B17: 1050 | C17: Polizas Soat
A18: 14 | B18: 1053 | C18: Turismo Orden
... A29: 25 | B29: 1067 | C29: Cupo Rotativo Avance
A30: 26
A31: 27
A32: 28
A33: 29
A34: 30
A35: 31
A36: 32
A37: 33
A38: 34
A39: 35
A40: 36
A41: 37
... A203: 199

Sheet Ponderación
A1: NUEVA PONDERACION
A2: 1. EDAD
A3: AÑOS | C3: PONDERACION
A4: 18-25 | C4: 2
A5: 26-45 | C5: 4
A6: 46-60 | C6: 3
A7: MAYOR DE 60 | C7: 1
C8: =SUM(C4:C7) -> 10
A9: 0. AHORROS EN EL FONDO | H9: PONDERACION GENERAL | I9: PROP
A10: 0 | B10: 0 | C10: 0 | H10: 1. NIVEL DE RIESGO | I10: 0.3
A11: 0 | B11: 0 | C11: 0 | H11: 0. AHORROS EN EL FONDO | I11: 0
A12: 0 | B12: 0 | C12: 0 | H12: 2. USUARIO DE CREDITO EN LA COOP | I12: 0.2
A13: 0 | B13: 0 | C13: 0 | H13: 3. EDAD | I13: 0.05
C14: =SUM(C10:C13) -> 0 | H14: 4. No PERSONAS A CARGO | I14: 0.05
A15: 2. USUARIO DE CREDITO EN EL FONDO | H15: 5. TIPO DE VIVIENDA | I15: 0.1
A16: 0 | B16: 1000000 | C16: 0 | H16: 6. ANTIGÜEDAD EN LA COOPERATIVA | I16: 0.15
A17: 1000000 | B17: 5000000 | C17: 1 | H17: 7. ANTIGÜEDAD LABORAL | I17: 0.1
A18: 5000000 | B18: 10000000 | C18: 3 | H18: 8. NIVEL DE INGRESOS | I18: 0.05
A19: 10000000 | C19: 6
C20: =SUM(C16:C19) -> 10 | I20: =SUM(I10:I19) -> 1
A21: 1. NIVEL DE RIESGO
A22: 0 | B22: 200 | C22: 0
A23: 201 | B23: 500 | C23: 1
A24: 501 | B24: 795 | C24: 2 | H24: PERFIL A | I24: ENTRE 4,01 A 5.83
A25: 796 | B25: 1000 | C25: 7 | H25: PERFIL B | I25: ENTRE 2.70 A 4.00
C26: =SUM(C22:C25) -> 10 | H26: PERFIL C | I26: ENTRE 0 A 2.69
I28: A | J28: 4.01 | K28: 5.83
I29: B | J29: 2.7 | K29: 4.00
I30: C | J30: 0 | K30: 2.69
A32: 1. EDAD
A33: AÑOS | C33: PONDERACION
A34: 18 | B34: 25 | C34: 2
A35: 26 | B35: 45 | C35: 4
A36: 46 | B36: 60 | C36: 3
A37: 60 | C37: 1
C38: =SUM(C34:C37) -> 10
A39: 4. No PERSONAS A CARGO
A40: 0 | B40: 1 | C40: 5
A41: 2 | B41: 3 | C41: 3
A42: 3 | B42: 4 | C42: 2
A43: 4 | C43: 0
C44: =SUM(C40:C43) -> 10
A45: 5.TIPO DE VIVIENDA
A46: FAMILIAR | B46: 4 | C46: 0
A47: ARRENDADA | B47: 2 | C47: 0
A48: PROPIA SIN HIPOTECA | B48: 1 | C48: 6
A49: HIPOTECADA | B49: 3 | C49: 4
A50: OTRAS | B50: 5 | C50: 0
C51: =SUM(C46:C50) -> 10
A52: 6.ANTIGÜEDAD EN COOPVALILI (Años)
A53: 0 | B53: 1 | C53: 1
A54: 1 | B54: 5 | C54: 2
A55: 5 | B55: 10 | C55: 3
A56: 10 | C56: 4
C57: =SUM(C53:C56) -> 10
A58: 7.ANTIGÜEDAD LABORAL (Años)
A59: 0 | B59: 1 | C59: 1
A60: 1 | B60: 5 | C60: 2
A61: 5 | B61: 10 | C61: 3
A62: 10 | C62: 4
C63: =SUM(C58:C62) -> 10
A64: 8. NIVEL DE INGRESOS
A65: 0 | B65: =+Parametros!$C$2*2 -> 3501810 | C65: 1
A66: =+Parametros!$C$2*2 -> 3501810 | B66: =+Parametros!$C$2*5 -> 8754525 | C66: 2
A67: =+Parametros!$C$2*5 -> 8754525 | B67: =+Parametros!$C$2*10 -> 17509050 | C67: 3
A68: =+Parametros!$C$2*10 -> 17509050 | C68: 4
C69: =SUM(C64:C68) -> 10

Sheet Base Perfil
K1: 0 | L1: 0.2 | M1: 0.3 | N1: 0.05 | O1: 0.05 | P1: 0.1 | Q1: 0.15 | R1: 0.1 | S1: 0.05
A2: DATOS DE ENTRADA | K2: CALCULOS | U2: RESULTADOS
A3: SCORE | B3: INGRESOS | C3: AHORROS_FONDO | D3: USARIO_CREDITO | E3: EDAD | F3: PERSONAS A CARGO | G3: TIPO_VIVIENDA | H3: ANTIGÜEDAD_FONDO | I3: ANTIGÜEDAD_LABORAL | K3: AHORROS FONDO | L3: USARIO_CREDITO | M3: SCOR_NIVEL_RIESGO | N3: SCOR_EDAD | O3: SCOR_PCARGO | P3: SCOR_VIVIENDA | Q3: SCOR_ANT_COOP | R3: SCOR_ANT_LABORAL | S3: SCOR_INGRESOS | U3: TOTALES_SCOR | V3: PERFILES
A4: =+Capacidad_Endeudamiento!$C$31 -> 657 | B4: =+Capacidad_Endeudamiento!$C$25 -> 2500000 | D4: 0 | E4: 38 | F4: 1 | G4: 4 | H4: 2.8194444 | I4: 3.0694444 | K4: 0 | L4: =+IF(D4="","",IF(AND(D4>=Ponderación!$A$16,D4<=Ponderación!$B$16),Ponderación!$C$16,IF(AND(D4>Ponderación!$B$16,D4<=Ponderación!$B$17),Ponderación!$C$17,IF(AND(D4>Ponderación!$B$17,D4<=Ponderación!$B$18),Ponderación!$C$18,IF(D4>Ponderación!$A$19,Ponderación!$C$19,"Revisar"))))) -> 0 | M4: =+IF(A4="","",IF(AND(A4>Ponderación!$A$22,A4<=Ponderación!$B$22),Ponderación!$C$22,IF(AND(A4>Ponderación!$B$22,A4<=Ponderación!$B$23),Ponderación!$C$23,IF(AND(A4>Ponderación!$B$23,A4<=Ponderación!$B$24),Ponderación!$C$24,IF(AND(A4>Ponderación!$B$24,A4<=Ponderación!$B$25),Ponderación!$C$25,0))))) -> 2 | N4: =+IF(E4="","",IF(AND(E4>Ponderación!$A$34,E4<=Ponderación!$B$34),Ponderación!$C$34,IF(AND(E4>Ponderación!$B$34,E4<=Ponderación!$B$35),Ponderación!$C$35,IF(AND(E4>Ponderación!$B$35,E4<=Ponderación!$B$36),Ponderación!$C$36,IF(E4>Ponderación!$B$36,Ponderación!$C$37))))) -> 4 | O4: =+IF(F4="","",IF(AND(F4>=Ponderación!$A$40,F4<=Ponderación!$B$40),Ponderación!$C$40,IF(AND(F4>=Ponderación!$A$41,F4<=Ponderación!$B$41),Ponderación!$C$41,IF(AND(F4>=Ponderación!$A$42,F4<=Ponderación!$B$42),Ponderación!$C$42,IF(F4>Ponderación!$A$43,Ponderación!$C$43))))) -> 5 | P4: =+IF(G4="","",IF(G4=Ponderación!$B$46,Ponderación!$C$46,IF(G4=Ponderación!$B$47,Ponderación!$C$47,IF(G4=Ponderación!$B$48,Ponderación!$C$48,IF(G4=Ponderación!$B$49,Ponderación!$C$49,IF(G4=Ponderación!$B$50,0)))))) -> 0 | Q4: =+IF(H4="","",IF(AND(H4>=Ponderación!$A$53,H4<=Ponderación!$B$53),Ponderación!$C$53,IF(AND(H4>Ponderación!$B$53,H4<=Ponderación!$B$54),Ponderación!$C$54,IF(AND(H4>Ponderación!$B$54,H4<=Ponderación!$B$55),Ponderación!$C$55,IF(H4>Ponderación!$B$55,Ponderación!$C$56))))) -> 2 | R4: =+IF(I4="","",IF(AND(I4>=Ponderación!$A$59,I4<=Ponderación!$B$59),Ponderación!$C$59,IF(AND(I4>=Ponderación!$B$59,I4<=Ponderación!$B$60),Ponderación!$C$60,IF(AND(I4>Ponderación!$B$60,I4<=Ponderación!$B$61),Ponderación!$C$61,IF(I4>Ponderación!$B$61,Ponderación!$C$62))))) -> 2 | S4: =+IF(B4="","",IF(AND(B4>=Ponderación!$A$65,B4<=Ponderación!$B$65),Ponderación!$C$65,IF(AND(B4>Ponderación!$B$65,B4<=Ponderación!$B$66),Ponderación!$C$66,IF(AND(B4>Ponderación!$B$66,B4<=Ponderación!$B$67),Ponderación!$C$67,IF(B4>Ponderación!$A$68,Ponderación!$C$68))))) -> 1 | U4: =+IF(R4="","",(K4*$K$1)+(L4*$L$1)+(M4*$M$1)+(N4*$N$1)+(O4*$O$1)+(P4*$P$1)+(Q4*$Q$1)+(R4*$R$1)+(S4*$S$1)) -> 1.6 | V4: =+IF(U4="","",IFERROR(IF(AND(U4>=Ponderación!$J$28,U4<=Ponderación!$K$28),Ponderación!$I$28,IF(AND(U4>=Ponderación!$J$29,U4<=Ponderación!$K$29),Ponderación!$I$29,IF(AND(U4>=Ponderación!$J$30,U4<=Ponderación!$K$30),Ponderación!$I$30))),"Retirado")) -> C
A5: TU | B5: Base_Asociados | D5: API | E5: Base_Asociados | F5: chat input | G5: Base_Asociados | H5: Base_Asociados | I5: Base_Asociados
K6: =+IF(C4="","",IF(AND(C4>=Ponderación!$A$10,C4<=Ponderación!$B$10),Ponderación!$C$10,IF(AND(C4>Ponderación!$B$10,C4<=Ponderación!$B$11),Ponderación!$C$11,IF(AND(C4>Ponderación!$B$11,C4<=Ponderación!$B$12),Ponderación!$C$12,IF(C4>Ponderación!$A$13,Ponderación!$C$13,"Revisar")))))
U7: =+IF(S7="","",(K7*$K$1)+(L7*$L$1)+(M7*$M$1)+(N7*$N$1)+(O7*$O$1)+(P7*$P$1)+(Q7*$Q$1)+(R7*$R$1)+(S7*$S$1))
B8: Egresos Segurdad Social | C8: Minimo Vital | D8: Cuota_Sector | F8: Descuento Empresa | H8: Total Egresos
A9: Egresos Asociados | B9: =+Capacidad_Endeudamiento!$C$27 -> 200000 | C9: =+Capacidad_Endeudamiento!$C$38 -> 1250000 | D9: =+Datos_Iniciales!$C$14 -> 0 | F9: =+Datos_Iniciales!$C$13 -> 476010 | H9: =+SUM(B9:G9) -> 1926010

Sheet Evaluacion de Cartera
C1: =+IFERROR(VLOOKUP(B1,'[2]14 Análisis Limites'!$E$4:$H$613,4,FALSE()),0) -> 0 | D1: =+IFERROR(VLOOKUP(B1,'[3]14 Análisis Limites'!$E$4:$H$610,4,FALSE()),0) -> 0
B2: CC | C2: 2021 | D2: 2022 | E2: 2023
B3: 4661060 | C3: 51.605201 | D3: 43.213333 | E3: 12.521034
B4: 6135820 | C4: 10.176924 | D4: 13.3444 | E4: 8.1892857
B5: 6421806 | C5: 59.094988 | D5: 20.622667 | E5: 7.892069
B6: 8834375 | C6: 38.164896 | D6: 30.4458 | E6: 26.673966
B7: 9104444 | C7: 4.6458036 | D7: 14.067111 | E7: 16.124641
B8: 10280915 | C8: 3.5389843 | D8: 1.7104444 | E8: 0
B9: 11830463 | C9: 11.24899 | D9: 7.5826667 | E9: 8.1396552
B10: 14590506 | C10: 24.688656 | D10: 36.4296 | E10: 25.172414
B11: 14590768 | C11: 8.9166408 | D11: 5.6244 | E11: 5.2339655
B12: 14621610 | C12: 17.855295 | D12: 7.7293333 | E12: 0
B13: 14797927 | C13: 20.268728 | D13: 43.951333 | E13: 6.5644828
B14: 14837882 | C14: 3.3606083 | D14: 11.2268 | E14: 0
... B894: 1234196269 | C894: 0 | D894: 47.677 | E894: 0.078275862

Sheet BD
B1: COOPERATIVA DE TRABAJODRES DE LA FUNDACIÓN VALLE DEL LILI
B2: BASE DE DATOS CREDITOS ANALIZADOS
B4: Auxiliar | C4: =+COUNTA($B$5:$B$1048576)+5 -> 904
B5: N° CEDULA | C5: ASOCIADO | D5: EMPRESA | E5: SALARIO | F5: LÍNEA DE CRÉDITO | G5: MONTO SOLICITADO | H5: SCOR CIFIN | I5: ENDEUDAMIENTO ACTUAL | J5: ENDEUDAMIENTO PROYECTADO | K5: CME | L5: CMD | M5: PERFIL | N5: SOLVENCIA | O5: NIVEL_EDEUDAMIENTO | P5: TASA | Q5: GARANTIA | R5: DEUDA SECTOR | S5: OBSERVACIONES | T5: FECHA
B6: 5208653 | C6: Guerrero Rosero Jesus Orlando | D6: FVL | E6: 4480000 | F6: Compra Cartera | G6: 0 | H6: 0 | I6: 0 | K6: 22.35251 | M6: C | N6: 0.58 | O6: 22.35251 | P6: 0.0099 | Q6: Aportes | R6: 100000000 | S6: 0 | T6: 45264.661
B7: 1234190116 | C7: Ortega Conda Hebert Augusto | D7: FVL | E7: 2320800 | F7: Educativo | G7: 6548095 | H7: 810 | I7: 0.41 | J7: 0.47 | K7: 6.4249832 | L7: 0.47 | M7: B | N7: 1.5768675 | O7: 6.4249832 | P7: 0.0099 | Q7: Aportes | R7: 11563000 | S7: 0 | T7: 45303.588
B8: 1010091223 | C8: Gonzalez Triviño Karen Yuliana | D8: FVL | E8: 2383300 | F8: Credito Ordinario | G8: 4600000 | H8: 657 | I8: 0.35 | J8: 0.39 | K8: 3.2102232 | L8: 0.39 | M8: C | N8: 0.96911341 | O8: 3.2102232 | P8: 0.0099 | Q8: Aportes | R8: 163000 | S8: 0 | T8: 45303.614
B9: 1010091223 | C9: Gonzalez Triviño Karen Yuliana | D9: FVL | E9: 2383300 | F9: Credito Ordinario | G9: 3000000 | H9: 657 | I9: 0.35 | J9: 0.38 | K9: 3.2102232 | L9: 0.38 | M9: C | N9: 0.96911341 | O9: 3.2102232 | P9: 0.0099 | Q9: Aportes | R9: 163000 | S9: TIENE CREDITO AFIANZADORA | T9: 45303.624
B10: 30398858 | C10: Osorio Toro Carolina | D10: FUNDACION VALLE DEL LILI | E10: 5890200 | F10: Credito Ordinario | G10: 1600000 | H10: 747 | I10: 0.36 | J10: 0.37 | K10: 4.6435223 | L10: 0.37 | M10: C | N10: 1.5133787 | O10: 4.6435223 | P10: 0.0227 | Q10: Aportes | R10: 18050000 | S10: TIENE CREDITO AFIANZADORA | T10: 45306.354
B11: 30398858 | C11: Osorio Toro Carolina | D11: FUNDACION VALLE DEL LILI | E11: 5890200 | F11: Credito Ordinario | G11: 1600000 | H11: 747 | I11: 0.36 | J11: 0.37 | K11: 4.6435223 | L11: 0.37 | M11: C | N11: 1.5133787 | O11: 4.6435223 | P11: 0.0227 | Q11: Aportes | R11: 18050000 | S11: TIENE CREDITO AFIANZADORA | T11: 45306.356
B12: 1130605624 | C12: Pillimue Del Campo Yulieth Andrea | D12: FUNDACION VALLE DEL LILI | E12: 2648100 | F12: Educativo | G12: 6228000 | H12: 775 | I12: 0.41 | J12: 0.46 | K12: 70.736146 | L12: 0.46 | M12: B | N12: 1.5895249 | O12: 70.736146 | P12: 0.006 | Q12: Aportes | R12: 184653000 | S12: TIENE CREDITO AFIANZADORA | T12: 45306.404
B13: 1130609546 | C13: Soto Velez John Stiven | D13: FUNDACION VALLE DEL LILI | E13: 2648100 | F13: Credito Ordinario | G13: 15000000 | H13: 806 | I13: 0.3 | J13: 0.49 | K13: 2.9953552 | L13: 0.49 | M13: B | N13: 1.3515203 | O13: 2.9953552 | P13: 0.0227 | Q13: Aportes | R13: 7932000 | S13: 0 | T13: 45306.426
B14: 94492338 | C14: Millan Taguado Wilmer Jose | D14: FUNDACION VALLE DEL LILI | E14: 9417000 | F14: Credito Ordinario | G14: 3000000 | H14: 805 | I14: 0.21 | J14: 0.22 | K14: 1.1670933 | L14: 0.22 | M14: B | N14: 0.67878687 | O14: 1.1670933 | P14: 0.0227 | Q14: Aportes | R14: 0 | S14: tiene cesantias pignoradas | T14: 45306.491
B15: 1010081973 | C15: Arboleda Cuene Danessa Alejandra | D15: FUNDACION VALLE DEL LILI | E15: 2648100 | F15: Credito Ordinario | G15: 2000000 | H15: 665 | I15: 0.49 | J15: 0.46 | K15: 10.81308 | L15: 0.46 | M15: C | N15: 1.2535259 | O15: 10.81308 | P15: 0.0227 | Q15: Aportes | R15: 20451000 | S15: tiene cesantias pignoradas | T15: 45306.591
B16: 1144076114 | C16: Alzate Arce Juan Esteban | D16: FUNDACION VALLE DEL LILI | E16: 1856600 | F16: Credito Ordinario | G16: 2300000 | H16: 657 | I16: 0.07 | J16: 0.11 | K16: 0.48852742 | L16: 0.11 | M16: C | N16: 1.2985716 | O16: 0.48852742 | P16: 0.0227 | Q16: Aportes | R16: 907000 | S16: 0 | T16: 45307.36
B17: 38886733 | C17: Vela Zambrano Jakeline | D17: FUNDACION VALLE DEL LILI | E17: 4867100 | F17: Credito Afianzadora | G17: 10000000 | H17: 705 | I17: 0.35 | J17: 0.42 | K17: 17.894257 | L17: 0.42 | M17: B | N17: 1.4183068 | O17: 17.894257 | P17: 0.0222 | Q17: Aportes | R17: 77509000 | S17: 0 | T17: 45307.411
B18: 1085662084 | C18: Ortega Ortega Herson Orlando | D18: FUNDACION VALLE DEL LILI | E18: 2383300 | F18: Cred.Ord. Gerencia | G18: 1700000 | H18: 555 | I18: 0.17 | J18: 0.21 | K18: 28.826549 | L18: 0.21 | M18: C | N18: 1.6969395 | O18: 28.826549 | P18: 0.0227 | Q18: Aportes | R18: 67153000 | S18: 0 | T18: 45307.446
B19: 1123626223 | C19: Martinez Gomez Diego Alejandro | D19: FUNDACION VALLE DEL LILI | E19: 3266300 | F19: Cred.Ord. Gerencia | G19: 3000000 | H19: 726 | I19: 0.25 | J19: 0.34 | K19: 8.1073386 | L19: 0.34 | M19: C | N19: 1.3338854 | O19: 8.1073386 | P19: 0.0227 | Q19: Aportes | R19: 26481000 | S19: 0 | T19: 45307.452
B20: 1143931949 | C20: Parra Hurtado Juan Carlos | D20: FUNDACION VALLE DEL LILI | E20: 1821900 | F20: Cred.Ord. Gerencia | G20: 3480000 | H20: 578 | I20: 0.3 | J20: 0.4 | K20: 1.083638 | L20: 0.4 | M20: C | N20: 1.2293825 | O20: 1.083638 | P20: 0.0227 | Q20: Aportes | R20: 820000 | S20: recoge creditos | T20: 45307.465
B21: 1116267848 | C21: Salazar Idrobo Laura Daniela | D21: FUNDACION VALLE DEL LILI | E21: 2383300 | F21: Compra Cartera | G21: 5105000 | H21: 871 | I21: 0.06 | J21: 0.18 | K21: 0.48432006 | L21: 0.18 | M21: B | N21: 0.89696933 | O21: 0.48432006 | P21: 0.018 | Q21: Aportes | R21: 0 | S21: recoge creditos | T21: 45307.578
B22: 1113673170 | C22: Orejuela Zuñiga Yessica Lorena | D22: FUNDACION VALLE DEL LILI | E22: 2320800 | F22: Compra Cartera | G22: 2000000 | H22: 744 | I22: 0.23 | J22: 0.28 | K22: 8.3567511 | L22: 0.28 | M22: C | N22: 1.06414 | O22: 8.3567511 | P22: 0.018 | Q22: Aportes | R22: 18142000 | S22: recoge creditos | T22: 45310.712
B23: 66717390 | C23: Cruz Galvez Sandra Milena | D23: FUNDACION VALLE DEL LILI | E23: 2320800 | F23: Cred.Ord. Gerencia | G23: 1500000 | H23: 747 | I23: 0.33 | J23: 0.34 | K23: 10.951312 | L23: 0.34 | M23: C | N23: 1.0082721 | O23: 10.951312 | P23: 0.0227 | Q23: Aportes | R23: 21858000 | S23: recoge creditos | T23: 45313.556
B24: 1061543239 | C24: Zuñiga Capote Karem Julieth | D24: FUNDACION VALLE DEL LILI | E24: 2320800 | F24: Cred.Ord. Gerencia | G24: 3000000 | H24: 739 | I24: 0.13 | J24: 0.18 | K24: 3.0317132 | L24: 0.18 | M24: C | N24: 0.83609833 | O24: 3.0317132 | P24: 0.0227 | Q24: Aportes | R24: 7036000 | S24: recoge creditos | T24: 45313.699
B25: 1085661067 | C25: Solarte Martinez Yohana Estefany | D25: FUNDACION VALLE DEL LILI | E25: 2648100 | F25: Credito Ordinario | G25: 4200000 | H25: 619 | I25: 0.23 | J25: 0.4 | K25: 6.8777614 | L25: 0.4 | M25: C | N25: 4.6720384 | O25: 6.8777614 | P25: 0.0227 | Q25: Aportes | R25: 18213000 | S25: 0 | T25: 45314.318
B26: 1144175903 | C26: Agudelo Ospina Marilyn Gisela | D26: COOPVALILI | E26: 1874704 | F26: Credito Ordinario | G26: 5000000 | H26: 692 | I26: 0.25 | J26: 0.34 | K26: 17.310666 | L26: 0.34 | M26: B | N26: 1.7087025 | O26: 17.310666 | P26: 0.0227 | Q26: Aportes | R26: 18780000 | S26: 0 | T26: 45314.708
B27: 1144175903 | C27: Agudelo Ospina Marilyn Gisela | D27: COOPVALILI | E27: 1874704 | F27: Credito Afianzadora | G27: 5000000 | H27: 692 | I27: 0.25 | J27: 0.34 | K27: 17.310666 | L27: 0.34 | M27: B | N27: 1.7087025 | O27: 17.310666 | P27: 0.0227 | Q27: Aportes | R27: 18780000 | S27: 0 | T27: 45314.714
B28: 1113308071 | C28: Linares Ortiz Tatiana | D28: FUNDACION VALLE DEL LILI | E28: 2648100 | F28: Ptmo.Ord.No24 | G28: 8600000 | H28: 471 | I28: 0.59 | J28: 0.7 | K28: 18.602972 | L28: 0.7 | M28: C | N28: 2.5334472 | O28: 18.602972 | P28: 0.0227 | Q28: Aportes | R28: 46539000 | S28: 0 | T28: 45315.321
B29: 1116267848 | C29: Salazar Idrobo Laura Daniela | D29: FUNDACION VALLE DEL LILI | E29: 2383300 | F29: Compra Cartera | G29: 5470000 | H29: 835 | I29: 0.05 | J29: 0.13 | K29: 34.578945 | L29: 0.13 | M29: B | N29: 1.9155826 | O29: 34.578945 | P29: 0.0227 | Q29: Aportes | R29: 82352000 | S29: 0 | T29: 45315.325
B30: 1143991760 | C30: Salcedo Rodriguez Nathalia | D30: FUNDACION VALLE DEL LILI | E30: 2320800 | F30: Cred.Ord. Gerencia | G30: 3000000 | H30: 514 | I30: 0.26 | J30: 0.34 | K30: 14.933229 | L30: 0.34 | M30: C | N30: 1.203295 | O30: 14.933229 | P30: 0.0227 | Q30: Aportes | R30: 29399000 | S30: tiene credito afianzadora | T30: 45315.331
B31: 34614231 | C31: Escobar Lopez Giovanna | D31: FUNDACION VALLE DEL LILI - HONORARIOS | E31: 4500000 | F31: Cred.Ord. Gerencia | G31: 4500000 | H31: 621 | I31: 0.66 | J31: 0.7 | K31: 20.910617 | L31: 0.7 | M31: C | N31: 2.2853567 | O31: 20.910617 | P31: 0.0227 | Q31: Aportes | R31: 90984000 | S31: tiene credito afianzadora | T31: 45315.361
B32: 1107081197 | C32: Ramirez Valencia Maria Del Mar | D32: FUNDACION VALLE DEL LILI | E32: 4984600 | F32: Ptmo.Ord.No24 | G32: 5000000 | H32: 677 | I32: 0.33 | J32: 0.39 | K32: 21.378958 | L32: 0.39 | M32: C | N32: 2.0784737 | O32: 21.378958 | P32: 0.0227 | Q32: Aportes | R32: 106367000 | S32: 0 | T32: 45315.369
B33: 94460501 | C33: Bolaños Ceballos John Marlon | D33: FUNDACION VALLE DEL LILI | E33: 4480000 | F33: Ptmo.Ord.No24 | G33: 16700000 | H33: 964 | I33: 0.27 | J33: 0.38 | K33: 2.253233 | L33: 0.38 | M33: A | N33: 0.82431049 | O33: 2.253233 | P33: 0.0199 | Q33: Aportes | R33: 0 | S33: pignora cesantias | T33: 45315.379
B34: 1130675011 | C34: Hidalgo Gomez Diana Maria | D34: FUNDACION VALLE DEL LILI | E34: 2320800 | F34: Ptmo.Ord.No24 | G34: 4000000 | H34: 784 | I34: 0.37 | J34: 0.42 | K34: 27.662929 | L34: 0.42 | M34: C | N34: 1.6895833 | O34: 27.662929 | P34: 0.0227 | Q34: Aportes | R34: 57274000 | S34: pignora cesantias | T34: 45315.386
B35: 60406095 | C35: Prato Hernandez Rosa Margarita | D35: FUNDACION VALLE DEL LILI | E35: 5374700 | F35: Ptmo.Ord.No24 | G35: 4500000 | H35: 665 | I35: 0.34 | J35: 0.38 | K35: 15.355712 | L35: 0.38 | M35: C | N35: 1.3696031 | O35: 15.355712 | P35: 0.0227 | Q35: Aportes | R35: 82352000 | S35: 0 | T35: 45315.393
B36: 1112465080 | C36: Rivas Mora Marlon | D36: FUNDACION VALLE DEL LILI | E36: 2320800 | F36: Cred.Ord. Gerencia | G36: 1700000 | H36: 555 | I36: 0.1 | J36: 0.17 | K36: 2.0667921 | L36: 0.17 | M36: C | N36: 1.2157248 | O36: 2.0667921 | P36: 0.0227 | Q36: Aportes | R36: 3063000 | S36: 0 | T36: 45315.621
B37: 38563522 | C37: Rodriguez Zapata Yaneth Milena | D37: FUNDACION VALLE DEL LILI | E37: 2320800 | F37: Cred.Ord. Gerencia | G37: 1000000 | H37: 608 | I37: 0.35 | J37: 0.37 | K37: 21.311776 | L37: 0.37 | M37: B | N37: 5.1740727 | O37: 21.311776 | P37: 0.0227 | Q37: Aportes | R37: 36616000 | S37: tiene afianzadora | T37: 45316.399
B38: 38873740 | C38: Hernandez Yusti Maria Cristina | D38: FUNDACION VALLE DEL LILI | E38: 2648100 | F38: Cred.Ord. Gerencia | G38: 2700000 | H38: 976 | I38: 0.31 | J38: 0.34 | K38: 2.05838 | L38: 0.34 | M38: B | N38: 0.8689551 | O38: 2.05838 | P38: 0.0227 | Q38: Aportes | R38: 0 | S38: 0 | T38: 45316.507
B39: 1144078618 | C39: Cortes Molina Leydi Vanessa | D39: FUNDACION VALLE DEL LILI | E39: 2320800 | F39: Cred.Ord. Gerencia | G39: 4000000 | H39: 706 | I39: 0.47 | J39: 0.57 | K39: 23.716495 | L39: 0.57 | M39: B | N39: 1.9009863 | O39: 23.716495 | P39: 0.0227 | Q39: Aportes | R39: 47644000 | S39: tiene afianzadora | T39: 45316.566
B40: 1144179107 | C40: Balanta Castellar Kelly Johanna | D40: FUNDACION VALLE DEL LILI | E40: 2648100 | F40: Cred.Ord. Gerencia | G40: 1300000 | H40: 603 | I40: 0.29 | J40: 0.32 | K40: 9.0045776 | L40: 0.32 | M40: C | N40: 1.0203119 | O40: 9.0045776 | P40: 0.0227 | Q40: Aportes | R40: 20498000 | S40: 0 | T40: 45316.575
B41: 16767193 | C41: Gomez Morera Juan Carlos | D41: FUNDACION VALLE DEL LILI | E41: 6946500 | F41: Cred.Ord. Gerencia | G41: 5000000 | H41: 576 | I41: 0.04 | J41: 0.07 | K41: 29.206795 | L41: 0.07 | M41: C | N41: 0.91381142 | O41: 29.206795 | P41: 0.0227 | Q41: Aportes | R41: 202885000 | S41: 0 | T41: 45316.687
B42: 34613504 | C42: Ospina Bermudez Leidy Diana | D42: FUNDACION VALLE DEL LILI | E42: 4486200 | F42: Cred.Ord. Gerencia | G42: 3000000 | H42: 589 | I42: 0.5 | J42: 0.52 | K42: 28.346485 | L42: 0.52 | M42: C | N42: 1.7945823 | O42: 28.346485 | P42: 0.0227 | Q42: Aportes | R42: 127168000 | S42: 0 | T42: 45317.321
B43: 1014205514 | C43: Perez Villa Yully Andrea | D43: FUNDACION VALLE DEL LILI | E43: 4032000 | F43: Orden Comercio | G43: 1729000 | H43: 632 | I43: 0.5 | J43: 0.54 | K43: 22.507688 | L43: 0.54 | M43: C | N43: 1.6775045 | O43: 22.507688 | P43: 0.0227 | Q43: Aportes | R43: 90751000 | S43: 0 | T43: 45317.329
B44: 1006179442 | C44: Gomez Muñoz Maria Angelica | D44: FUNDACION VALLE DEL LILI | E44: 2383300 | F44: Cred.Ord. Gerencia | G44: 1900000 | H44: 640 | I44: 0.14 | J44: 0.23 | K44: 2.1520606 | L44: 0.23 | M44: C | N44: 1.0006701 | O44: 2.1520606 | P44: 0.0227 | Q44: Aportes | R44: 2691000 | S44: 0 | T44: 45317.363
B45: 1144052596 | C45: Granada Montealegre Javier Andrey | D45: FUNDACION VALLE DEL LILI | E45: 1450000 | F45: Cred.Ord. Gerencia | G45: 1900000 | H45: 608 | I45: 0.18 | J45: 0.24 | K45: 1.2453586 | L45: 0.24 | M45: C | N45: 1.4205248 | O45: 1.2453586 | P45: 0.0227 | Q45: Aportes | R45: 0 | S45: 0 | T45: 45317.378
B46: 1062312895 | C46: Arrieta Yucuma Andres Felipe | D46: FUNDACION VALLE DEL LILI | E46: 2320800 | F46: Cred.Ord. Gerencia | G46: 2400000 | H46: 701 | I46: 0.31 | J46: 0.37 | K46: 7.3786548 | L46: 0.37 | M46: C | N46: 1.2196333 | O46: 7.3786548 | P46: 0.0227 | Q46: Aportes | R46: 15057000 | S46: 0 | T46: 45317.392
B47: 16889110 | C47: Opance Collo Milton Lider | D47: FUNDACION VALLE DEL LILI | E47: 1755600 | F47: Cred.Ord. Gerencia | G47: 1300000 | H47: 687 | I47: 0.24 | J47: 0.29 | K47: 8.1551156 | L47: 0.29 | M47: C | N47: 2.3127535 | O47: 8.1551156 | P47: 0.0227 | Q47: Aportes | R47: 11412000 | S47: 0 | T47: 45317.403
B48: 1054990766 | C48: Correa Giraldo Cristian Andres | D48: FUNDACION VALLE DEL LILI | E48: 2088700 | F48: Cred.Ord. Gerencia | G48: 900000 | H48: 760 | I48: 0.19 | J48: 0.22 | K48: 14.292685 | L48: 0.22 | M48: C | N48: 13.361781 | O48: 14.292685 | P48: 0.0227 | Q48: Aportes | R48: 28000000 | S48: 0 | T48: 45317.432
B49: 1054990766 | C49: Correa Giraldo Cristian Andres | D49: FUNDACION VALLE DEL LILI | E49: 2088700 | F49: Cred.Ord. Gerencia | G49: 3700000 | H49: 760 | I49: 0.36 | J49: 0.46 | K49: 13.405468 | L49: 0.46 | M49: C | N49: 1.6853224 | O49: 13.405468 | P49: 0.0227 | Q49: Aportes | R49: 28000000 | S49: 0 | T49: 45317.441
B50: 1107507036 | C50: Gaviria Erazo Sergio Enrique | D50: FUNDACION VALLE DEL LILI | E50: 2088700 | F50: Cred.Ord. Gerencia | G50: 900000 | H50: 553 | I50: 0.07 | J50: 0.1 | K50: 14.37982 | L50: 0.1 | M50: C | N50: 13.25013 | O50: 14.37982 | P50: 0.0227 | Q50: Aportes | R50: 28182000 | S50: 0 | T50: 45317.447
B51: 1097399265 | C51: Maldonado Marin Hever Andres | D51: FUNDACION VALLE DEL LILI | E51: 2320800 | F51: Cred.Ord. Gerencia | G51: 2000000 | H51: 589 | I51: 0.38 | J51: 0.4 | K51: 16.626594 | L51: 0.4 | M51: C | N51: 1.6854692 | O51: 16.626594 | P51: 0.0227 | Q51: Aportes | R51: 38587000 | S51: 0 | T51: 45317.494
... B56: 66851685 | C56: Cardenas Hernandez Maria Esmeralda | D56: ASOCIACION VOLUNTARIADO FCVL | E56: 1420000 | F56: Cred.Ord. Gerencia | G56: 3500000 | H56: 747 | I56: 1.09 | J56: 1.2 | K56: 8.113207 | L56: 1.2 | M56: B | N56: 1.7419718 | O56: 8.113207 | P56: 0.0227 | Q56: Aportes | R56: 5583000 | S56: 0 | T56: 45321.598
B57: 94074218 | C57: Ortiz Grisales Telmo | D57: FUNDACION VALLE DEL LILI | E57: 1912300 | F57: Credito Afianzadora | G57: 10000000 | H57: 726 | I57: 0.24 | J57: 0.32 | K57: 9.3417021 | L57: 0.32 | M57: B | N57: 1.1650557 | O57: 9.3417021 | P57: 0.0222 | Q57: Aportes | R57: 4347000 | S57: TIENE VEHICULO PIGNORADO Y RESPALDA ESTE REDITO CON AFIANZADORA | T57: 45322.423
B58: 1144175903 | C58: Agudelo Ospina Marilyn Gisela | D58: COOPVALILI | E58: 2318500 | F58: Credito Afianzadora | G58: 10000000 | H58: 692 | I58: 0.2 | J58: 0.26 | K58: 7.7050408 | L58: 0.26 | M58: B | N58: 1.0625542 | O58: 7.7050408 | P58: 0.0222 | Q58: Aportes | R58: 4347000 | S58: TIENE VEHICULO PIGNORADO Y RESPALDA ESTE REDITO CON AFIANZADORA | T58: 45322.424
B59: 1144126183 | C59: Rocha Gutierrez Cindy Yulied | D59: FUNDACION VALLE DEL LILI | E59: 2648100 | F59: Educativo | G59: 6552000 | H59: 843 | I59: 0.07 | J59: 0.19 | K59: 0.37762924 | L59: 0.19 | M59: B | N59: 0.64553453 | O59: 0.37762924 | P59: 0.006 | Q59: Aportes | R59: 1000000 | S59: 0 | T59: 45322.429
B60: 52057091 | C60: Mercado Tobias Ana Carolina | D60: FUNDACION VALLE DEL LILI | E60: 4867100 | F60: Credito Afianzadora | G60: 3800000 | H60: 873 | I60: 0.36 | J60: 0.44 | K60: 0.12492038 | L60: 0.44 | M60: A | N60: 1.0402542 | O60: 0.12492038 | P60: 0.0222 | Q60: Aportes | R60: 608000 | S60: 0 | T60: 45322.433
B61: 1107528770 | C61: Mesa Ospina Maria Camila | D61: FUNDACION VALLE DEL LILI | E61: 1450000 | F61: Cred.Ord. Gerencia | G61: 2900000 | H61: 679 | I61: 0.18 | J61: 0.29 | K61: 10.481166 | L61: 0.29 | M61: C | N61: 1.5864124 | O61: 10.481166 | P61: 0.0227 | Q61: Aportes | R61: 14958000 | S61: 0 | T61: 45323.498
B62: 66846381 | C62: Barajas Carbonell Amanda Eugenia | D62: FUNDACION VALLE DEL LILI | E62: 2320800 | F62: Cred.Ord. Gerencia | G62: 3600000 | H62: 746 | I62: 0.1 | J62: 0.13 | K62: 37.429335 | L62: 0.13 | M62: C | N62: 0.71099018 | O62: 37.429335 | P62: 0.0227 | Q62: Aportes | R62: 86866000 | S62: 0 | T62: 45323.566
B63: 1010086359 | C63: Restrepo Trujillo Shakira Andrea | D63: FUNDACION VALLE DEL LILI | E63: 2648100 | F63: Cred.Ord. Gerencia | G63: 4000000 | H63: 686 | I63: 0.22 | J63: 0.28 | K63: 19.314372 | L63: 0.28 | M63: C | N63: 1.4388543 | O63: 19.314372 | P63: 0.0227 | Q63: Aportes | R63: 49283000 | S63: 0 | T63: 45323.568
B64: 1114884602 | C64: Gaviria Diaz Duber Alexis | D64: FUNDACION VALLE DEL LILI | E64: 2320800 | F64: Cred.Ord. Gerencia | G64: 2000000 | H64: 810 | I64: 0.46 | J64: 0.51 | K64: 14.793606 | L64: 0.51 | M64: B | N64: 1.5126508 | O64: 14.793606 | P64: 0.0227 | Q64: Aportes | R64: 34333000 | S64: 0 | T64: 45323.57
B65: 94043124 | C65: Velez Valencia Pablo Alejandro | D65: FUNDACION VALLE DEL LILI | E65: 4984600 | F65: Cred.Ord. Gerencia | G65: 2000000 | H65: 618 | I65: 0.52 | J65: 0.55 | K65: 19.573652 | L65: 0.55 | M65: C | N65: 2.847202 | O65: 19.573652 | P65: 0.0227 | Q65: Aportes | R65: 90225000 | S65: tiene garantia afianzadora | T65: 45323.595
B66: 38464115 | C66: Lozano Valderrama Ana Maria | D66: FUNDACION VALLE DEL LILI | E66: 2648100 | F66: Cred.Ord. Gerencia | G66: 2500000 | H66: 837 | I66: 0.44 | J66: 0.54 | K66: 21.668558 | L66: 0.54 | M66: B | N66: 1.7641347 | O66: 21.668558 | P66: 0.0227 | Q66: Aportes | R66: 57108000 | S66: 0 | T66: 45323.598
B67: 38464115 | C67: Lozano Valderrama Ana Maria | D67: FUNDACION VALLE DEL LILI | E67: 2648100 | F67: Cred.Ord. Gerencia | G67: 2500000 | H67: 837 | I67: 0.44 | J67: 0.54 | K67: 21.668558 | L67: 0.54 | M67: B | N67: 1.7641347 | O67: 21.668558 | P67: 0.0227 | Q67: Aportes | R67: 57108000 | S67: 0 | T67: 45323.598
B68: 34613050 | C68: Ortiz Niño Luz Marina | D68: FUNDACION VALLE DEL LILI | E68: 2648100 | F68: Credito Afianzadora | G68: 15000000 | H68: 726 | I68: 0.53 | J68: 0.72 | K68: 9.4438416 | L68: 0.72 | M68: B | N68: 1.0643174 | O68: 9.4438416 | P68: 0.0227 | Q68: Aportes | R68: 0 | S68: 0 | T68: 45323.696
B69: 1112483089 | C69: Viveros Viafara Jhan Camilo | D69: FUNDACION VALLE DEL LILI | E69: 2648100 | F69: Cred.Ord. Gerencia | G69: 1500000 | H69: 666 | I69: 0.34 | J69: 0.37 | K69: 5.6207692 | L69: 0.37 | M69: C | N69: 1.0142789 | O69: 5.6207692 | P69: 0.0227 | Q69: Aportes | R69: 4536000 | S69: tiene afianzadora como respaldo | T69: 45327.626
B70: 25341987 | C70: Valencia Cobo Eliana | D70: FUNDACION VALLE DEL LILI | E70: 1450000 | F70: Cred.Ord. Gerencia | G70: 2900000 | H70: 582 | I70: 0.1 | J70: 0.22 | K70: 11.366498 | L70: 0.22 | M70: C | N70: 1.0034345 | O70: 11.366498 | P70: 0.0227 | Q70: Aportes | R70: 16325000 | S70: tiene afianzadora como respaldo | T70: 45327.629
B71: 1113692973 | C71: Castillo Valdes Julithza | D71: FUNDACION VALLE DEL LILI | E71: 3699900 | F71: Educativo | G71: 2295000 | H71: 725 | I71: 0.05 | J71: 0.06 | K71: 2.526211 | L71: 0.06 | M71: C | N71: 0.93532528 | O71: 2.526211 | P71: 0.0227 | Q71: Aportes | R71: 9266000 | S71: 0 | T71: 45327.65
B72: 1144090457 | C72: Cuero Caicedo Geidy Vanessa | D72: FUNDACION VALLE DEL LILI | E72: 1450000 | F72: Cred.Ord. Gerencia | G72: 1700000 | H72: 632 | I72: 0.18 | J72: 0.25 | K72: 1.1746607 | L72: 0.25 | M72: C | N72: 0.79047103 | O72: 1.1746607 | P72: 0.0227 | Q72: Aportes | R72: 131000 | S72: 0 | T72: 45327.661
B73: 1130635783 | C73: Medina Lozano Yuliana | D73: FUNDACION VALLE DEL LILI | E73: 1450000 | F73: Cred.Ord. Gerencia | G73: 1500000 | H73: 540 | I73: 0.46 | J73: 0.51 | K73: 18.611197 | L73: 0.51 | M73: C | N73: 3.9019614 | O73: 18.611197 | P73: 0.0227 | Q73: Aportes | R73: 25295000 | S73: 0 | T73: 45327.668
B74: 1144151327 | C74: Oyola Valderrama Claudia Ximena | D74: FUNDACION VALLE DEL LILI | E74: 2648100 | F74: Cred.Ord. Gerencia | G74: 1800000 | H74: 576 | I74: 0.39 | J74: 0.42 | K74: 13.603446 | L74: 0.42 | M74: C | N74: 2.5210611 | O74: 13.603446 | P74: 0.0227 | Q74: Aportes | R74: 33537000 | S74: 0 | T74: 45327.683
B75: 91493134 | C75: Coronell Martinez Aldemir Jose | D75: FUNDACION VALLE DEL LILI | E75: 3629200 | F75: Cred.Ord. Gerencia | G75: 1000000 | H75: 708 | I75: 0.39 | J75: 0.4 | K75: 8.697095 | L75: 0.4 | M75: C | N75: 1.3798578 | O75: 8.697095 | P75: 0.0227 | Q75: Aportes | R75: 31136000 | S75: 0 | T75: 45327.684
B76: 1130609348 | C76: Arenas Virgen Angela Maria | D76: FUNDACION VALLE DEL LILI | E76: 2648100 | F76: Cred.Ord. Gerencia | G76: 2000000 | H76: 724 | I76: 0.44 | J76: 0.48 | K76: 19.61485 | L76: 0.48 | M76: C | N76: 1.7712367 | O76: 19.61485 | P76: 0.0227 | Q76: Aportes | R76: 51733000 | S76: 0 | T76: 45327.686
B77: 1143945334 | C77: Cardona Aldana Lina Marcela | D77: FVL | E77: 2648100 | F77: Educativo | G77: 6548095 | H77: 863 | I77: 0.39 | J77: 0.63 | K77: 0.04768551 | L77: 0.63 | M77: B | N77: 2.099815 | O77: 0.04768551 | P77: 0.007 | Q77: Aportes | R77: 126276 | S77: 0 | T77: 45265.661
B78: 31574407 | C78: Varela Angucho Zeudy Janeth | D78: FVL | E78: 3629200 | F78: Educativo | G78: 5615000 | H78: 957 | I78: 0.16 | J78: 0.45 | K78: 1.1458404 | L78: 0.45 | M78: B | N78: 1.0522688 | O78: 1.1458404 | P78: 0.007 | Q78: Aportes | R78: 3954000 | S78: 0 | T78: 45265.666
B79: 1130639453 | C79: Villani Bahamon Carolina | D79: FVL | E79: 5374700 | F79: Credito Ordinario | G79: 5000000 | H79: 855 | I79: 0.17 | J79: 0.21 | K79: 2.6195116 | L79: 0.21 | M79: A | N79: 0.95713938 | O79: 2.6195116 | P79: 0.0199 | Q79: Aportes | R79: 10087000 | S79: 0 | T79: 45265.689
B80: 1151944100 | C80: Rojas Bolaños Diana Carolina | D80: FVL | E80: 2320800 | F80: Credito Ordinario | G80: 6850000 | H80: 857 | I80: 0.2 | J80: 0.21 | K80: 2.136967 | L80: 0.21 | M80: A | N80: 1.0932144 | O80: 2.136967 | P80: 0.0199 | Q80: Aportes | R80: 0 | S80: 0 | T80: 45265.705
B81: 1130617413 | C81: Lorez Marquez Herman Alexander | D81: FVL | E81: 1450000 | F81: Credito Ordinario | G81: 2486556 | H81: 619 | I81: 0.31 | J81: 0.34 | K81: 11.905595 | L81: 0.34 | M81: C | N81: 1.2387593 | O81: 11.905595 | P81: 0.0199 | Q81: Aportes | R81: 15451000 | S81: 0 | T81: 45265.709
B82: 31532035 | C82: Gil Montilla Ivonny | D82: FVL | E82: 8359700 | F82: Educativo | G82: 12632050 | H82: 977 | I82: 0.15 | J82: 0.29 | K82: 0.51597139 | L82: 0.29 | M82: B | N82: 0.62367322 | O82: 0.51597139 | P82: 0.006 | Q82: Aportes | R82: 84000 | S82: 0 | T82: 45265.721
... B125: 9104444 | C125: Watts Pajaro Fredy Alejandro | D125: FUNDACION VALLE DEL LILI - HONORARIOS | E125: 34883879 | F125: Credito Ordinario | G125: 10000000 | H125: 642 | I125: 0.47 | J125: 0.47 | K125: 2.1819605 | L125: 0.47 | M125: B | N125: 1.609637 | O125: 2.1819605 | P125: 0.006 | Q125: Aportes | R125: 66854700 | S125: 0 | T125: 45328.752
B126: 1085267594 | C126: Seidel Aguilera Jacqueline | D126: FUNDACION VALLE DEL LILI | E126: 5347100 | F126: Credito Ordinario | G126: 5700000 | H126: 536 | I126: 0.12 | J126: 0.1 | K126: 24.531591 | L126: 0.1 | M126: C | N126: 1.0553365 | O126: 24.531591 | P126: 0.006 | Q126: Aportes | R126: 128353000 | S126: presenta codeudor y tiene buen score | T126: 45328.757
B127: 35424880 | C127: Navas Guzman Llady Cecilia | D127: FUNDACION VALLE DEL LILI | E127: 3980900 | F127: Credito Ordinario | G127: 6000000 | H127: 959 | I127: 0.11 | J127: 0.18 | K127: 1.0869464 | L127: 0.18 | M127: B | N127: 1.0387947 | O127: 1.0869464 | P127: 0.0199 | Q127: Aportes | R127: 2564000 | S127: 0 | T127: 45328.76
B128: 1143970362 | C128: Sanchez Morales Juliana Isabel | D128: FUNDACION VALLE DEL LILI | E128: 2648100 | F128: Credito Ordinario | G128: 9000000 | H128: 616 | I128: 0.45 | J128: 0.55 | K128: 22.660296 | L128: 0.55 | M128: C | N128: 1.4733488 | O128: 22.660296 | P128: 0.0199 | Q128: Aportes | R128: 59615000 | S128: 0 | T128: 45328.762
B129: 34613050 | C129: Ortiz Niño Luz Marina | D129: FUNDACION VALLE DEL LILI | E129: 2648100 | F129: Credito Afianzadora | G129: 15000000 | H129: 726 | I129: 0.53 | J129: 0.55 | K129: 9.4714086 | L129: 0.55 | M129: B | N129: 1.0918844 | O129: 9.4714086 | P129: 0.0199 | Q129: Aportes | R129: 73000 | S129: tiene garantia un vehiculo | T129: 45328.766
B130: 1005934361 | C130: Barrios Diez David Andres | D130: FUNDACION VALLE DEL LILI | E130: 4984600 | F130: Ptmo.Ord.No24 | G130: 5000000 | H130: 657 | I130: 0.24 | J130: 0.34 | K130: 9.6314649 | L130: 0.34 | M130: C | N130: 2.4042132 | O130: 9.6314649 | P130: 0.0199 | Q130: Aportes | R130: 48009000 | S130: 0 | T130: 45329.51
B131: 66949976 | C131: Quimbaya Gaviria Sandra Lucia | D131: FUNDACION VALLE DEL LILI | E131: 2648100 | F131: Ptmo.Ord.No24 | G131: 3410000 | H131: 886 | I131: 0.33 | J131: 0.34 | K131: 12.055675 | L131: 0.34 | M131: B | N131: 1.6648423 | O131: 12.055675 | P131: 0.0227 | Q131: Aportes | R131: 29937000 | S131: 0 | T131: 45330.654
B132: 66856977 | C132: Sanchez Morales Alba Lucy | D132: FUNDACION VALLE DEL LILI | E132: 7584800 | F132: Cred.Ord. Gerencia | G132: 2500000 | H132: 747 | I132: 0.39 | J132: 0.41 | K132: 2.8480524 | L132: 0.41 | M132: B | N132: 0.8494431 | O132: 2.8480524 | P132: 0.0227 | Q132: Aportes | R132: 0 | S132: 0 | T132: 45331.416
B133: 1143986684 | C133: Carmona Montoya Yeraldin | D133: FUNDACION VALLE DEL LILI | E133: 2088700 | F133: Cred.Ord. Gerencia | G133: 1000000 | H133: 592 | I133: 0.04 | J133: 0.09 | K133: 2.8515344 | L133: 0.09 | M133: C | N133: 0.84989659 | O133: 2.8515344 | P133: 0.0227 | Q133: Aportes | R133: 5956000 | S133: 0 | T133: 45331.563
B134: 67000591 | C134: Castaño Diana Consuelo | D134: FUNDACION VALLE DEL LILI | E134: 2648100 | F134: Cred.Ord. Gerencia | G134: 3000000 | H134: 677 | I134: 0.38 | J134: 0.42 | K134: 10.21823 | L134: 0.42 | M134: B | N134: 4.8975511 | O134: 10.21823 | P134: 0.0227 | Q134: Aportes | R134: 10314000 | S134: 0 | T134: 45331.583
B135: 1130670450 | C135: Montezuma Diaz Vanessa | D135: FUNDACION VALLE DEL LILI | E135: 2320800 | F135: Cred.Ord. Gerencia | G135: 1400000 | H135: 598 | I135: 0.44 | J135: 0.47 | K135: 12.400655 | L135: 0.47 | M135: C | N135: 1.4117873 | O135: 12.400655 | P135: 0.0227 | Q135: Aportes | R135: 25833000 | S135: 0 | T135: 45335.33
B136: 1116130515 | C136: Cuartas Arcila Sindy Fernanda | D136: FUNDACION VALLE DEL LILI | E136: 2648100 | F136: Credito De Vehiculo | G136: 8671000 | H136: 665 | I136: 0.19 | J136: 0.29 | K136: 12.852234 | L136: 0.29 | M136: C | N136: 1.0963566 | O136: 12.852234 | P136: 0.017 | Q136: Aportes | R136: 34034000 | S136: PIGNORA VEHICULO | T136: 45336.48
B137: 1085279770 | C137: Enriquez Ponce Maria Alejandra | D137: FUNDACION VALLE DEL LILI | E137: 7523500 | F137: Credito Ordinario | G137: 6000000 | H137: 588 | I137: 0.11 | J137: 0.2 | K137: 0 | L137: 0.2 | M137: C | N137: 0.78089878 | O137: 0 | P137: 0.017 | Q137: Aportes | R137: 0 | S137: 0 | T137: 45336.482
B138: 1144179639 | C138: Vargas Buritica Ingrith Nataly | D138: FUNDACION VALLE DEL LILI | E138: 2383300 | F138: Credito Ordinario | G138: 7000000 | H138: 642 | I138: 0.08 | J138: 0.2 | K138: 0.069947552 | L138: 0.2 | M138: C | N138: 0.65609869 | O138: 0.069947552 | P138: 0.017 | Q138: Aportes | R138: 0 | S138: 0 | T138: 45336.483
B139: 1144186978 | C139: Cisneros Garcia Mayra Alejandra | D139: FUNDACION VALLE DEL LILI | E139: 2320800 | F139: Credito Ordinario | G139: 4100000 | H139: 628 | I139: 0.46 | J139: 0.52 | K139: 10.706332 | L139: 0.52 | M139: C | N139: 1.0066861 | O139: 10.706332 | P139: 0.017 | Q139: Aportes | R139: 21991000 | S139: recoge creditos por valor de $ 2.034.819 | T139: 45336.493
B140: 1107081228 | C140: Chango Restrepo Brayan Stiven | D140: FUNDACION VALLE DEL LILI | E140: 2320800 | F140: Cred.Ord. Gerencia | G140: 4000000 | H140: 669 | I140: 0.33 | J140: 0.51 | K140: 3.3187832 | L140: 0.51 | M140: C | N140: 2.5015314 | O140: 3.3187832 | P140: 0.0227 | Q140: Aportes | R140: 6079000 | S140: 0 | T140: 45337.723
B141: 38612964 | C141: Idrobo Trochez Yomaira | D141: FUNDACION VALLE DEL LILI | E141: 2648100 | F141: Cred.Ord. Gerencia | G141: 3300000 | H141: 745 | I141: 0.3 | J141: 0.38 | K141: 16.202938 | L141: 0.38 | M141: C | N141: 1.2089475 | O141: 16.202938 | P141: 0.0227 | Q141: Aportes | R141: 42907000 | S141: 0 | T141: 45337.728
B142: 1059985209 | C142: Velasco Churi Lizeth | D142: FUNDACION VALLE DEL LILI | E142: 1490100 | F142: Cred.Ord. Gerencia | G142: 2500000 | H142: 682 | I142: 0.06 | J142: 0.12 | K142: 2.3743373 | L142: 0.12 | M142: C | N142: 1.1911892 | O142: 2.3743373 | P142: 0.0227 | Q142: Aportes | R142: 3538000 | S142: 0 | T142: 45337.733
B143: 1144161155 | C143: Nuñez Torres Douglas Alberto | D143: FUNDACION VALLE DEL LILI | E143: 1821900 | F143: Cred.Ord. Gerencia | G143: 700000 | H143: 632 | I143: 0.15 | J143: 0.19 | K143: 1.0640941 | L143: 0.19 | M143: C | N143: 0.75810802 | O143: 1.0640941 | P143: 0.0227 | Q143: Aportes | R143: 0 | S143: 0 | T143: 45338.406
B144: 1214738852 | C144: Berrio Botero Paula Andrea | D144: FUNDACION VALLE DEL LILI | E144: 1450000 | F144: Cred.Ord. Gerencia | G144: 2900000 | H144: 677 | I144: 0.13 | J144: 0.2 | K144: 3.1587145 | L144: 0.2 | M144: C | N144: 1.0272393 | O144: 3.1587145 | P144: 0.0227 | Q144: Aportes | R144: 4266000 | S144: 0 | T144: 45338.41
B145: 38683726 | C145: Orozco Guerrero Sandra Patricia | D145: FUNDACION VALLE DEL LILI | E145: 2088700 | F145: Cred.Ord. Gerencia | G145: 1400000 | H145: 440 | I145: 0.16 | J145: 0.2 | K145: 8.5579686 | L145: 0.2 | M145: C | N145: 3.8545449 | O145: 8.5579686 | P145: 0.0227 | Q145: Aportes | R145: 16137000 | S145: 0 | T145: 45338.449
B146: 1107518527 | C146: Bonilla Valencia Leidy Juliana | D146: FUNDACION VALLE DEL LILI | E146: 2648100 | F146: Cred.Ord. Gerencia | G146: 1500000 | H146: 582 | I146: 0.36 | J146: 0.4 | K146: 14.392372 | L146: 0.4 | M146: C | N146: 2.3323137 | O146: 14.392372 | P146: 0.0227 | Q146: Aportes | R146: 36424000 | S146: 0 | T146: 45338.452
B147: 1113695768 | C147: Hidalgo Lemos Darling Dayana | D147: FUNDACION VALLE DEL LILI | E147: 2088700 | F147: Cred.Ord. Gerencia | G147: 2400000 | H147: 632 | I147: 0.4 | J147: 0.44 | K147: 21.491516 | L147: 0.44 | M147: C | N147: 1.940372 | O147: 21.491516 | P147: 0.0227 | Q147: Aportes | R147: 43620000 | S147: 0 | T147: 45338.458
...

Sheet Parametros
B2: SMMLV 2024 | C2: 1750905
G3: Tipo de Contrato
B4: Protección de ley SMMLV | G4: Normal | H4: 0.08 | I4: 0
B5: =+$C$2*1 -> 1750905 | C5: =+$C$2*4 -> 7003620 | D5: 0.5 | G5: Integral | H5: 0.7
B6: =+$C$2*4 -> 7003620 | C6: =+$C$2*10 -> 17509050 | D6: 0.4 | G6: Pensionado | H6: 0.12
C7: =+$C$2*10 -> 17509050 | D7: 0.3
G8: Fondo de Solidaridad
B9: Tasa de Usura (Dic 2024) | C9: 0.3498 | D9: =+(1+C9)^(1/12)-1 -> 0.025311398 | G9: =+$C$2*4 -> 7003620 | H9: 0.09
B10: Plazo Tarjetas | D10: 36
G11: Intereses a las cesantias
H12: 0.12
B13: Rango atribuciones
B14: Desde | C14: Hasta | D14: Rango
B15: 0 | C15: 0 | D15: Jefe de Credito y Cartera
B16: 0 | C16: 4000000 | D16: Gerente
B17: 4000000 | C17: 9999999999 | D17: Comité de Credito
B18: 0 | C18: 0 | D18: Consejo de Administración
B20: Nivel de Endeudamiento
B21: Desde | C21: Hasta | D21: Rango
B22: 0 | C22: 15 | D22: Normal
B23: 15 | C23: 20 | D23: Ajustada
B24: > | C24: 20 | D24: Excepción
B26: Desprotegidos - Creditos no Afianzados
B27: Salario | D27: Perfil | E27: Nº SMMLV | F27: Valor Desprotegido | G27: 2023
B28: =+$C$2*$I$28 -> 1750905 | C28: =+$C$2*$J$28 -> 3501810 | D28: A | E28: 5 | F28: =+$C$2*E28 -> 8754525 | G28: 5800000 | I28: 1 | J28: 2
B29: =+$C$2*$I$28 -> 1750905 | C29: =+$C$2*$J$28 -> 3501810 | D29: B | E29: 4 | F29: =+$C$2*E29 -> 7003620 | G29: 4640000
B30: =+$C$2*$I$28 -> 1750905 | C30: =+$C$2*$J$28 -> 3501810 | D30: C | E30: 2 | F30: =+$C$2*E30 -> 3501810 | G30: 2320000
B31: =+$C$2*$I$31+1 -> 3501811 | C31: =+$C$2*$J$31 -> 7003620 | D31: A | E31: 8 | F31: =+$C$2*E31 -> 14007240 | G31: 9280000 | I31: 2 | J31: 4
B32: =+$C$2*$I$31+1 -> 3501811 | C32: =+$C$2*$J$31 -> 7003620 | D32: B | E32: 5 | F32: =+$C$2*E32 -> 8754525 | G32: 5800000
B33: =+$C$2*$I$31+1 -> 3501811 | C33: =+$C$2*$J$31 -> 7003620 | D33: C | E33: 2 | F33: =+$C$2*E33 -> 3501810 | G33: 2320000
B34: =+$C$2*$I$34+1 -> 7003621 | D34: A | E34: 11 | F34: =+$C$2*E34 -> 19259955 | G34: 12760000 | I34: 4
B35: =+$C$2*$I$34+1 -> 7003621 | D35: B | E35: 6 | F35: =+$C$2*E35 -> 10505430 | G35: 6960000
B36: =+$C$2*$I$34+1 -> 7003621 | D36: C | E36: 2 | F36: =+$C$2*E36 -> 3501810 | G36: 2320000
B38: Desprotegidos - Creditos Afianzados
B39: Perfil | C39: Nº SMMLV | D39: Desprotegido | E39: 2023
B40: A | C40: 14 | D40: =+$C$2*C40 -> 24512670 | E40: 18560000 | F40: =+E40-D40 -> -5952670
B41: B | C41: 10 | D41: =+$C$2*C41 -> 17509050 | E41: 12760000 | F41: =+E41-D41 -> -4749050
B44: Analistas | D44: Jefes
B45: Lorena Jimenez | D45: Hugo Fernando Dávila
B46: Diana Martinez | D46: Comité de Credito
B47: Marilyn Agudelo | D47: Consejo de Administración
B48: Emily Valencia
B49: Camila Murillo

Sheet Score_Cifin
A1: TIPO_IDENTIFICACION | B1: NUMERO_IDENTIFICACION | C1: CREDITVISION
A2: 1 | B2: 40087405 | C2: 747
A3: 1 | B3: 1144128860 | C3: 794
A4: 1 | B4: 11320970 | C4: 816
A5: 1 | B5: 1130643699 | C5: 632
A6: 1 | B6: 1118282261 | C6: 747
A7: 1 | B7: 66773669 | C7: 784
A8: 1 | B8: 1087118163 | C8: 605
A9: 1 | B9: 38561848 | C9: 557
A10: 1 | B10: 1130595126 | C10: 861
A11: 1 | B11: 31576196 | C11: 910
A12: 1 | B12: 1144067925 | C12: 803
A13: 1 | B13: 1151939688 | C13: 770
... A1782: 1 | B1782: 1144097364 | C1782: 598

Sheet Base_Asociados
B1: COOPERATIVA DE TRABAJODRES DE LA FUNDACIÓN VALLE DEL LILI | L1: =+TODAY() -> 46154 | S1: =+TODAY() -> 46154 | AK1: EMPRESA
B2: BASE DE DATOS ASOCIADOS A JUNIO 2023 | L2: =+_xlfn.DAYS($L$1,L1049)/365 -> 3.1616438 | M2: =+_xlfn.DAYS($L$1,M1049)/365 -> 3.4082192 | AK2: AGRICOLA EL CABUYAL
H3: -1
B4: INFORMACION BASE DE DATOS COOPVALILI | R4: FORMULAS | AK4: AGRODEC
B5: Cedula | C5: apellido | D5: nombre | E5: ciudad | F5: estado civil | G5: Salario | H5: aportes | I5: deuda Coopvalili | J5: edad | K5: Tipo Vivienda | L5: Fecha Ing Coopvalili | M5: Fecha Ing FVL | N5: personas a cargo | O5: Empresa | P5: Nivel | Q5: Cuota Disponible FVL | R5: ASOCIADO | S5: Antigüedad en la Cooperativa | T5: Antigüedad Laboral | U5: Usuario De Credito en Coopvalili | V5: ESTADO_CIVIL
B6: 4661060 | C6: MINA | D6: ROBERTO CARLOS | E6: CALI | F6: Union libre | G6: 2600900 | H6: 3332046 | I6: 7023445 | J6: 43 | K6: 2 | L6: 43654 | M6: 38875 | N6: 1 | O6: FUNDACION VALLE DEL LILI | P6: =VLOOKUP(B6,'NIVEL ENERO'!A:D,3,0) -> 0.39337458 | Q6: =VLOOKUP(B6,'NIVEL ENERO'!A:D,4,0) -> 88218.54 | R6: =+PROPER(C6&" "&D6) -> Mina Roberto Carlos | S6: =+YEARFRAC(L6,$S$1) -> 6.8444444 | T6: =+YEARFRAC(M6,$S$1) -> 19.930556 | U6: =+$I6 -> 7023445 | V6: =+PROPER(F6) -> Union Libre
B7: 4759062 | C7: BALANTA MINA | D7: GENEZAID | E7: CALI | F7: Casado(a) | G7: 2100000 | H7: 13049396 | I7: 0 | J7: 66 | K7: 2 | L7: 39786 | M7: 34350 | N7: 4 | O7: ADMINISTRADOR COLOMBIANA DE PENSIONES | P7: =VLOOKUP(B7,'NIVEL ENERO'!A:D,3,0) -> #N/A | Q7: =VLOOKUP(B7,'NIVEL ENERO'!A:D,4,0) -> #N/A | R7: =+PROPER(C7&" "&D7) -> Balanta Mina Genezaid | S7: =+YEARFRAC(L7,$S$1) -> 17.438889 | T7: =+YEARFRAC(M7,$S$1) -> 32.322222 | U7: =+$I7 -> 0 | V7: =+PROPER(F7) -> Casado(A)
B8: 5208653 | C8: GUERRERO ROSERO | D8: JESUS ORLANDO | E8: CALI | F8: Casado(a) | G8: 8245400 | H8: 3133300 | I8: 0 | J8: 44 | K8: 1 | L8: 43817 | M8: 43452 | N8: 2 | O8: FUNDACION VALLE DEL LILI | P8: =VLOOKUP(B8,'NIVEL ENERO'!A:D,3,0) -> 0.16265461 | Q8: =VLOOKUP(B8,'NIVEL ENERO'!A:D,4,0) -> 2163256.9 | R8: =+PROPER(C8&" "&D8) -> Guerrero Rosero Jesus Orlando | S8: =+YEARFRAC(L8,$S$1) -> 6.4 | T8: =+YEARFRAC(M8,$S$1) -> 7.4 | U8: =+$I8 -> 0 | V8: =+PROPER(F8) -> Casado(A)
B9: 5824652 | C9: CARVAJAL JIMENEZ | D9: CARLOS ANDRES | E9: CALI | F9: Soltero(a) | G9: 2089800 | H9: 5329875 | I9: 7507873 | J9: 43 | K9: 2 | L9: 43817 | M9: 40344 | N9: 3 | O9: FUNDACION VALLE DEL LILI | P9: =VLOOKUP(B9,'NIVEL ENERO'!A:D,3,0) -> 0.48223088 | Q9: =VLOOKUP(B9,'NIVEL ENERO'!A:D,4,0) -> -222943 | R9: =+PROPER(C9&" "&D9) -> Carvajal Jimenez Carlos Andres | S9: =+YEARFRAC(L9,$S$1) -> 6.4 | T9: =+YEARFRAC(M9,$S$1) -> 15.908333 | U9: =+$I9 -> 7507873 | V9: =+PROPER(F9) -> Soltero(A)
B10: 6098612 | C10: TORO GARCIA | D10: JOHN FABIO | E10: CALI | F10: Casado(a) | G10: 1625000 | H10: 1180060 | I10: 95250 | J10: 45 | K10: 1 | L10: 45096 | M10: 44964 | N10: 0 | O10: FUNDACION VALLE DEL LILI | P10: =VLOOKUP(B10,'NIVEL ENERO'!A:D,3,0) -> 0.4019979 | Q10: =VLOOKUP(B10,'NIVEL ENERO'!A:D,4,0) -> 69651 | R10: =+PROPER(C10&" "&D10) -> Toro Garcia John Fabio | S10: =+YEARFRAC(L10,$S$1) -> 2.8972222 | T10: =+YEARFRAC(M10,$S$1) -> 3.2638889 | U10: =+$I10 -> 95250 | V10: =+PROPER(F10) -> Casado(A)
B11: 6135820 | C11: ROJAS GARCIA | D11: ALEXANDER | E11: CALI | F11: Soltero(a) | G11: 8245400 | H11: 7465998 | I11: 2911197 | J11: 43 | K11: 1 | L11: 42074 | M11: 42065 | N11: 2 | O11: FUNDACION VALLE DEL LILI | P11: =VLOOKUP(B11,'NIVEL ENERO'!A:D,3,0) -> 0.25286194 | Q11: =VLOOKUP(B11,'NIVEL ENERO'!A:D,4,0) -> 1408205 | R11: =+PROPER(C11&" "&D11) -> Rojas Garcia Alexander | S11: =+YEARFRAC(L11,$S$1) -> 11.169444 | T11: =+YEARFRAC(M11,$S$1) -> 11.194444 | U11: =+$I11 -> 2911197 | V11: =+PROPER(F11) -> Soltero(A)
B12: 6199680 | C12: GOMEZ GRISALES | D12: ALVARO HERNAN | E12: CALI | F12: Casado(a) | G12: 6247700 | H12: 3492610 | I12: 0 | J12: 44 | K12: 6 | L12: 43333 | M12: 40554 | N12: 4 | O12: FUNDACION VALLE DEL LILI | P12: =VLOOKUP(B12,'NIVEL ENERO'!A:D,3,0) -> 0.37801436 | Q12: =VLOOKUP(B12,'NIVEL ENERO'!A:D,4,0) -> 315230.64 | R12: =+PROPER(C12&" "&D12) -> Gomez Grisales Alvaro Hernan | S12: =+YEARFRAC(L12,$S$1) -> 7.725 | T12: =+YEARFRAC(M12,$S$1) -> 15.336111 | U12: =+$I12 -> 0 | V12: =+PROPER(F12) -> Casado(A)
B13: 6355880 | C13: MONDRAGON GORDILLO | D13: FERNELLY | E13: CALI | F13: Casado(a) | G13: 2298000 | H13: 5711566 | I13: 0 | J13: 68 | K13: 2 | L13: 41733 | M13: 41733 | N13: 2 | O13: ADMINISTRADOR COLOMBIANA DE PENSIONES | P13: =VLOOKUP(B13,'NIVEL ENERO'!A:D,3,0) -> #N/A | Q13: =VLOOKUP(B13,'NIVEL ENERO'!A:D,4,0) -> #N/A | R13: =+PROPER(C13&" "&D13) -> Mondragon Gordillo Fernelly | S13: =+YEARFRAC(L13,$S$1) -> 12.105556 | T13: =+YEARFRAC(M13,$S$1) -> 12.105556 | U13: =+$I13 -> 0 | V13: =+PROPER(F13) -> Casado(A)
B14: 6391199 | C14: ANDRADE BLANCO | D14: LUIS FERNANDO | E14: CALI | F14: Casado(a) | G14: 2916600 | H14: 4613628 | I14: 3516540 | J14: 43 | K14: 4 | L14: 44636 | M14: 40436 | N14: 4 | O14: FUNDACION VALLE DEL LILI | P14: =VLOOKUP(B14,'NIVEL ENERO'!A:D,3,0) -> 0.35000198 | Q14: =VLOOKUP(B14,'NIVEL ENERO'!A:D,4,0) -> 276853.6 | R14: =+PROPER(C14&" "&D14) -> Andrade Blanco Luis Fernando | S14: =+YEARFRAC(L14,$S$1) -> 4.1555556 | T14: =+YEARFRAC(M14,$S$1) -> 15.658333 | U14: =+$I14 -> 3516540 | V14: =+PROPER(F14) -> Casado(A)
B15: 6393613 | C15: TORO CORREA | D15: JOSE JOAQUIN | E15: CALI | F15: Union libre | G15: 18113200 | H15: 3444817 | I15: 61558704 | J15: 43 | K15: 4 | L15: 45096 | M15: 42121 | N15: 0 | O15: FUNDACION VALLE DEL LILI | P15: =VLOOKUP(B15,'NIVEL ENERO'!A:D,3,0) -> 0.38388767 | Q15: =VLOOKUP(B15,'NIVEL ENERO'!A:D,4,0) -> 755956.4 | R15: =+PROPER(C15&" "&D15) -> Toro Correa Jose Joaquin | S15: =+YEARFRAC(L15,$S$1) -> 2.8972222 | T15: =+YEARFRAC(M15,$S$1) -> 11.041667 | U15: =+$I15 -> 61558704 | V15: =+PROPER(F15) -> Union Libre
B16: 6537914 | C16: DELGADO ALVAREZ | D16: ALEXIS | E16: FLORIDA | F16: Soltero(a) | G16: 8245400 | H16: 2011731 | I16: 3143167 | J16: 44 | K16: 2 | L16: 44579 | M16: 40148 | N16: 4 | O16: FUNDACION VALLE DEL LILI | P16: =VLOOKUP(B16,'NIVEL ENERO'!A:D,3,0) -> 0.1642021 | Q16: =VLOOKUP(B16,'NIVEL ENERO'!A:D,4,0) -> 2109156 | R16: =+PROPER(C16&" "&D16) -> Delgado Alvarez Alexis | S16: =+YEARFRAC(L16,$S$1) -> 4.3166667 | T16: =+YEARFRAC(M16,$S$1) -> 16.447222 | U16: =+$I16 -> 3143167 | V16: =+PROPER(F16) -> Soltero(A)
B17: 6550905 | C17: VIDAL BUENO | D17: JORGE HERNAN | E17: CALI | F17: Union libre | G17: 4870200 | H17: 1600537 | I17: 1389409 | J17: 40 | K17: 3 | L17: 45191 | M17: 41593 | N17: 0 | O17: FUNDACION VALLE DEL LILI | P17: =VLOOKUP(B17,'NIVEL ENERO'!A:D,3,0) -> 0.35995955 | Q17: =VLOOKUP(B17,'NIVEL ENERO'!A:D,4,0) -> 391637.36 | R17: =+PROPER(C17&" "&D17) -> Vidal Bueno Jorge Hernan | S17: =+YEARFRAC(L17,$S$1) -> 2.6388889 | T17: =+YEARFRAC(M17,$S$1) -> 12.491667 | U17: =+$I17 -> 1389409 | V17: =+PROPER(F17) -> Union Libre
B18: 9292583 | C18: LAMBRANO BARRERA | D18: RAFAEL ARMANDO | E18: CALI | F18: Casado(a) | G18: 5679200 | H18: 2304741 | J18: 47 | K18: 1 | L18: 44977 | M18: 40954 | N18: 0 | O18: FUNDACION VALLE DEL LILI | P18: =VLOOKUP(B18,'NIVEL ENERO'!A:D,3,0) -> 0.26760543 | Q18: =VLOOKUP(B18,'NIVEL ENERO'!A:D,4,0) -> 1461723 | R18: =+PROPER(C18&" "&D18) -> Lambrano Barrera Rafael Armando | S18: =+YEARFRAC(L18,$S$1) -> 3.2277778 | T18: =+YEARFRAC(M18,$S$1) -> 14.241667 | U18: =+$I18 -> 0 | V18: =+PROPER(F18) -> Casado(A)
B19: 10280915 | C19: TRUJILLO ARANGO | D19: GERMAN HUMBERTO | E19: CALI | F19: Casado(a) | G19: 19690900 | H19: 5133080 | I19: 3963132 | J19: 56 | K19: 6 | L19: 37987 | M19: 36913 | N19: 2 | O19: FUNDACION VALLE DEL LILI | P19: =VLOOKUP(B19,'NIVEL ENERO'!A:D,3,0) -> 0.47565441 | Q19: =VLOOKUP(B19,'NIVEL ENERO'!A:D,4,0) -> -1187939.9 | R19: =+PROPER(C19&" "&D19) -> Trujillo Arango German Humberto | S19: =+YEARFRAC(L19,$S$1) -> 22.363889 | T19: =+YEARFRAC(M19,$S$1) -> 25.305556 | U19: =+$I19 -> 3963132 | V19: =+PROPER(F19) -> Casado(A)
B20: 10285994 | C20: CORREA GARCIA | D20: ORLANDO | E20: CALI | F20: Union libre | G20: 5418800 | H20: 21421217 | I20: 0 | J20: 55 | K20: 1 | L20: 40076 | M20: 40066 | N20: 3 | O20: FUNDACION VALLE DEL LILI | P20: =VLOOKUP(B20,'NIVEL ENERO'!A:D,3,0) -> 0.17595909 | Q20: =VLOOKUP(B20,'NIVEL ENERO'!A:D,4,0) -> 1861721.8 | R20: =+PROPER(C20&" "&D20) -> Correa Garcia Orlando | S20: =+YEARFRAC(L20,$S$1) -> 16.644444 | T20: =+YEARFRAC(M20,$S$1) -> 16.672222 | U20: =+$I20 -> 0 | V20: =+PROPER(F20) -> Union Libre
B21: 10294212 | C21: HURTADO PABON | D21: HARRY FABIAN | E21: CALI | F21: Union libre | G21: 4469100 | H21: 2570104 | I21: 1152580 | J21: 42 | K21: 2 | L21: 44579 | M21: 44155 | N21: 4 | O21: FUNDACION VALLE DEL LILI | P21: =VLOOKUP(B21,'NIVEL ENERO'!A:D,3,0) -> 0.15254105 | Q21: =VLOOKUP(B21,'NIVEL ENERO'!A:D,4,0) -> 1642759 | R21: =+PROPER(C21&" "&D21) -> Hurtado Pabon Harry Fabian | S21: =+YEARFRAC(L21,$S$1) -> 4.3166667 | T21: =+YEARFRAC(M21,$S$1) -> 5.4777778 | U21: =+$I21 -> 1152580 | V21: =+PROPER(F21) -> Union Libre
B22: 10567677 | C22: ORDONEZ PALECHOR | D22: MARIO GENTIL | E22: JAMUNDÍ | F22: Union libre | G22: 1670000 | H22: 2420842 | I22: 1112457 | J22: 45 | K22: 2 | L22: 44274 | M22: 42787 | N22: 3 | O22: FUNDACION VALLE DEL LILI | P22: =VLOOKUP(B22,'NIVEL ENERO'!A:D,3,0) -> 0.36013304 | Q22: =VLOOKUP(B22,'NIVEL ENERO'!A:D,4,0) -> 131217.3 | R22: =+PROPER(C22&" "&D22) -> Ordonez Palechor Mario Gentil | S22: =+YEARFRAC(L22,$S$1) -> 5.1472222 | T22: =+YEARFRAC(M22,$S$1) -> 9.225 | U22: =+$I22 -> 1112457 | V22: =+PROPER(F22) -> Union Libre
B23: 10723755 | C23: HURTADO HURTADO | D23: JOHN JAMES | E23: CALI | F23: Soltero(a) | G23: 4870200 | H23: 1300011 | J23: 39 | K23: 2 | L23: 45279 | M23: 41074 | N23: 0 | O23: FUNDACION VALLE DEL LILI | P23: =VLOOKUP(B23,'NIVEL ENERO'!A:D,3,0) -> 0.22224371 | Q23: =VLOOKUP(B23,'NIVEL ENERO'!A:D,4,0) -> 1086921.6 | R23: =+PROPER(C23&" "&D23) -> Hurtado Hurtado John James | S23: =+YEARFRAC(L23,$S$1) -> 2.3972222 | T23: =+YEARFRAC(M23,$S$1) -> 13.911111 | U23: =+$I23 -> 0 | V23: =+PROPER(F23) -> Soltero(A)
B24: 11320970 | C24: HERNANDEZ CHAVEZ | D24: CARLOS HOLMES | E24: CALI | F24: Union libre | G24: 5374700 | H24: 3298561 | I24: 0 | J24: 52 | K24: 4 | L24: 43627 | M24: 34821 | N24: 4 | O24: FUNDACION VALLE DEL LILI | P24: =VLOOKUP(B24,'NIVEL ENERO'!A:D,3,0) -> 0.42754621 | Q24: =VLOOKUP(B24,'NIVEL ENERO'!A:D,4,0) -> -56033.88 | R24: =+PROPER(C24&" "&D24) -> Hernandez Chavez Carlos Holmes | S24: =+YEARFRAC(L24,$S$1) -> 6.9194444 | T24: =+YEARFRAC(M24,$S$1) -> 31.027778 | U24: =+$I24 -> 0 | V24: =+PROPER(F24) -> Union Libre
B25: 11620559 | C25: MOSQUERA PALACIO | D25: EVIS JOTH | E25: CALI | F25: Union libre | G25: 2600900 | H25: 905339 | I25: 1430597 | J25: 45 | K25: 1 | L25: 45370 | M25: 44781 | N25: 1 | O25: FUNDACION VALLE DEL LILI | P25: =VLOOKUP(B25,'NIVEL ENERO'!A:D,3,0) -> 0.3896538 | Q25: =VLOOKUP(B25,'NIVEL ENERO'!A:D,4,0) -> 81558.32 | R25: =+PROPER(C25&" "&D25) -> Mosquera Palacio Evis Joth | S25: =+YEARFRAC(L25,$S$1) -> 2.1472222 | T25: =+YEARFRAC(M25,$S$1) -> 3.7611111 | U25: =+$I25 -> 1430597 | V25: =+PROPER(F25) -> Union Libre
B26: 11830463 | C26: HINESTROZA GAMBOA | D26: CELIMO | E26: CALI | F26: Union libre | G26: 1918500 | H26: 3682544 | I26: 4123050 | J26: 54 | K26: 4 | L26: 43392 | M26: 43200 | N26: 4 | O26: FUNDACION VALLE DEL LILI | P26: =VLOOKUP(B26,'NIVEL ENERO'!A:D,3,0) -> 0.40318424 | Q26: =VLOOKUP(B26,'NIVEL ENERO'!A:D,4,0) -> 76812 | R26: =+PROPER(C26&" "&D26) -> Hinestroza Gamboa Celimo | S26: =+YEARFRAC(L26,$S$1) -> 7.5638889 | T26: =+YEARFRAC(M26,$S$1) -> 8.0888889 | U26: =+$I26 -> 4123050 | V26: =+PROPER(F26) -> Union Libre
B27: 13069223 | C27: JOJOA HERNANDEZ | D27: MILTON ALEXANDER | E27: CALI | F27: Casado(a) | G27: 13588800 | H27: 6790485 | I27: 614601 | J27: 46 | K27: 2 | L27: 44245 | M27: 41075 | N27: 3 | O27: FUNDACION VALLE DEL LILI | P27: =VLOOKUP(B27,'NIVEL ENERO'!A:D,3,0) -> 0.22942232 | Q27: =VLOOKUP(B27,'NIVEL ENERO'!A:D,4,0) -> 2589722 | R27: =+PROPER(C27&" "&D27) -> Jojoa Hernandez Milton Alexander | S27: =+YEARFRAC(L27,$S$1) -> 5.2333333 | T27: =+YEARFRAC(M27,$S$1) -> 13.908333 | U27: =+$I27 -> 614601 | V27: =+PROPER(F27) -> Casado(A)
B28: 14465776 | C28: CANAMEJOY GARCIA | D28: JUAN PABLO | E28: CALI | F28: Soltero(a) | G28: 3945300 | H28: 4411459 | I28: 2352123 | J28: 42 | K28: 1 | L28: 44328 | M28: 40238 | N28: 4 | O28: FUNDACION VALLE DEL LILI | P28: =VLOOKUP(B28,'NIVEL ENERO'!A:D,3,0) -> 0.46233948 | Q28: =VLOOKUP(B28,'NIVEL ENERO'!A:D,4,0) -> -188224.8 | R28: =+PROPER(C28&" "&D28) -> Canamejoy Garcia Juan Pablo | S28: =+YEARFRAC(L28,$S$1) -> 5 | T28: =+YEARFRAC(M28,$S$1) -> 16.197222 | U28: =+$I28 -> 2352123 | V28: =+PROPER(F28) -> Soltero(A)
B29: 14479754 | C29: ANGULO SEGURA | D29: ARVEY | E29: CALI | F29: Soltero(a) | G29: 1625000 | H29: 1910716 | I29: 5827259 | J29: 40 | K29: 2 | L29: 44635 | M29: 44099 | N29: 0 | O29: FUNDACION VALLE DEL LILI | P29: =VLOOKUP(B29,'NIVEL ENERO'!A:D,3,0) -> 0.36114628 | Q29: =VLOOKUP(B29,'NIVEL ENERO'!A:D,4,0) -> 129546.98 | R29: =+PROPER(C29&" "&D29) -> Angulo Segura Arvey | S29: =+YEARFRAC(L29,$S$1) -> 4.1583333 | T29: =+YEARFRAC(M29,$S$1) -> 5.6305556 | U29: =+$I29 -> 5827259 | V29: =+PROPER(F29) -> Soltero(A)
B30: 14590768 | C30: LLOREDA MEJIA | D30: LUIS FRANCISCO | E30: CALI | F30: Separado(a) | G30: 5418800 | H30: 3476448 | I30: 10166088 | J30: 42 | K30: 2 | L30: 44155 | M30: 39756 | N30: 2 | O30: FUNDACION VALLE DEL LILI | P30: =VLOOKUP(B30,'NIVEL ENERO'!A:D,3,0) -> 0.26518277 | Q30: =VLOOKUP(B30,'NIVEL ENERO'!A:D,4,0) -> 1231980.9 | R30: =+PROPER(C30&" "&D30) -> Lloreda Mejia Luis Francisco | S30: =+YEARFRAC(L30,$S$1) -> 5.4777778 | T30: =+YEARFRAC(M30,$S$1) -> 17.522222 | U30: =+$I30 -> 10166088 | V30: =+PROPER(F30) -> Separado(A)
B31: 14607266 | C31: RAMOS LASSO | D31: JULIAN | E31: CALI | F31: Union libre | G31: 5418800 | H31: 4414912 | I31: 4045957 | J31: 42 | K31: 1 | L31: 45051 | M31: 40589 | N31: 4 | O31: FUNDACION VALLE DEL LILI | P31: =VLOOKUP(B31,'NIVEL ENERO'!A:D,3,0) -> 0.17074916 | Q31: =VLOOKUP(B31,'NIVEL ENERO'!A:D,4,0) -> 1794590.1 | R31: =+PROPER(C31&" "&D31) -> Ramos Lasso Julian | S31: =+YEARFRAC(L31,$S$1) -> 3.0194444 | T31: =+YEARFRAC(M31,$S$1) -> 15.241667 | U31: =+$I31 -> 4045957 | V31: =+PROPER(F31) -> Union Libre
B32: 14608276 | C32: MEZA TORRES | D32: EDWAR ERNESTO | E32: CALI | F32: Casado(a) | G32: 2600900 | H32: 1015322 | J32: 41 | K32: 1 | L32: 45191 | M32: 44365 | N32: 0 | O32: FUNDACION VALLE DEL LILI | P32: =VLOOKUP(B32,'NIVEL ENERO'!A:D,3,0) -> 0.11933907 | Q32: =VLOOKUP(B32,'NIVEL ENERO'!A:D,4,0) -> 781989 | R32: =+PROPER(C32&" "&D32) -> Meza Torres Edwar Ernesto | S32: =+YEARFRAC(L32,$S$1) -> 2.6388889 | T32: =+YEARFRAC(M32,$S$1) -> 4.9 | U32: =+$I32 -> 0 | V32: =+PROPER(F32) -> Casado(A)
B33: 14608714 | C33: DIAZ MENESES | D33: DAVID ORLANDO | E33: CALI | F33: Union libre | G33: 5418800 | H33: 15238115 | I33: 12143696 | J33: 41 | K33: 1 | L33: 40526 | M33: 39756 | N33: 4 | O33: FUNDACION VALLE DEL LILI | P33: =VLOOKUP(B33,'NIVEL ENERO'!A:D,3,0) -> 0.18836387 | Q33: =VLOOKUP(B33,'NIVEL ENERO'!A:D,4,0) -> 1768999.1 | R33: =+PROPER(C33&" "&D33) -> Diaz Meneses David Orlando | S33: =+YEARFRAC(L33,$S$1) -> 15.411111 | T33: =+YEARFRAC(M33,$S$1) -> 17.522222 | U33: =+$I33 -> 12143696 | V33: =+PROPER(F33) -> Union Libre
B34: 14609734 | C34: MONTANO PRECIADO | D34: JHON FREDDY | E34: CALI | F34: Union libre | G34: 1625000 | H34: 2283663 | I34: 2187024 | J34: 40 | K34: 2 | L34: 44398 | M34: 44175 | N34: 3 | O34: FUNDACION VALLE DEL LILI | P34: =VLOOKUP(B34,'NIVEL ENERO'!A:D,3,0) -> 0.27381485 | Q34: =VLOOKUP(B34,'NIVEL ENERO'!A:D,4,0) -> 316837.8 | R34: =+PROPER(C34&" "&D34) -> Montano Preciado Jhon Freddy | S34: =+YEARFRAC(L34,$S$1) -> 4.8083333 | T34: =+YEARFRAC(M34,$S$1) -> 5.4222222 | U34: =+$I34 -> 2187024 | V34: =+PROPER(F34) -> Union Libre
B35: 14621610 | C35: MUNOZ VALERO | D35: ALVARO | E35: CALI | F35: Soltero(a) | G35: 4761900 | H35: 6363376 | I35: 0 | J35: 41 | K35: 1 | L35: 42871 | M35: 37043 | N35: 1 | O35: FUNDACION VALLE DEL LILI | P35: =VLOOKUP(B35,'NIVEL ENERO'!A:D,3,0) -> 0.22452655 | Q35: =VLOOKUP(B35,'NIVEL ENERO'!A:D,4,0) -> 930825 | R35: =+PROPER(C35&" "&D35) -> Munoz Valero Alvaro | S35: =+YEARFRAC(L35,$S$1) -> 8.9888889 | T35: =+YEARFRAC(M35,$S$1) -> 24.947222 | U35: =+$I35 -> 0 | V35: =+PROPER(F35) -> Soltero(A)
B36: 14638297 | C36: ARANGO NARVAEZ | D36: OSCAR EDUARDO | E36: CALI | F36: Union libre | G36: 5418800 | H36: 3718870 | I36: 1898217 | J36: 40 | K36: 1 | L36: 44519 | M36: 44393 | N36: 4 | O36: FUNDACION VALLE DEL LILI | P36: =VLOOKUP(B36,'NIVEL ENERO'!A:D,3,0) -> 0.38992453 | Q36: =VLOOKUP(B36,'NIVEL ENERO'!A:D,4,0) -> 221501.52 | R36: =+PROPER(C36&" "&D36) -> Arango Narvaez Oscar Eduardo | S36: =+YEARFRAC(L36,$S$1) -> 4.4805556 | T36: =+YEARFRAC(M36,$S$1) -> 4.8222222 | U36: =+$I36 -> 1898217 | V36: =+PROPER(F36) -> Union Libre
B37: 14638857 | C37: OCAMPO GALLEGO | D37: JONNATHAN | E37: CALI | F37: Union libre | G37: 5418800 | H37: 1256457 | I37: 375780 | J37: 40 | K37: 6 | L37: 45064 | M37: 40988 | N37: 2 | O37: FUNDACION VALLE DEL LILI | P37: =VLOOKUP(B37,'NIVEL ENERO'!A:D,3,0) -> 0.32302269 | Q37: =VLOOKUP(B37,'NIVEL ENERO'!A:D,4,0) -> 530831.8 | R37: =+PROPER(C37&" "&D37) -> Ocampo Gallego Jonnathan | S37: =+YEARFRAC(L37,$S$1) -> 2.9833333 | T37: =+YEARFRAC(M37,$S$1) -> 14.144444 | U37: =+$I37 -> 375780 | V37: =+PROPER(F37) -> Union Libre
B38: 14797927 | C38: WAGNER DIAZ | D38: JULIO ENRIQUE | E38: CALI | F38: Union libre | G38: 2600900 | H38: 5292123 | I38: 1522898 | J38: 42 | K38: 1 | L38: 42191 | M38: 42139 | N38: 2 | O38: FUNDACION VALLE DEL LILI | P38: =VLOOKUP(B38,'NIVEL ENERO'!A:D,3,0) -> 0.29916337 | Q38: =VLOOKUP(B38,'NIVEL ENERO'!A:D,4,0) -> 314284 | R38: =+PROPER(C38&" "&D38) -> Wagner Diaz Julio Enrique | S38: =+YEARFRAC(L38,$S$1) -> 10.85 | T38: =+YEARFRAC(M38,$S$1) -> 10.991667 | U38: =+$I38 -> 1522898 | V38: =+PROPER(F38) -> Union Libre
B39: 14837964 | C39: NINO MOTATO | D39: HUGO FERNANDO | E39: CALI | F39: Casado(a) | G39: 2893800 | H39: 2249657 | I39: 2462396 | J39: 44 | K39: 2 | L39: 44669 | M39: 39118 | N39: 3 | O39: FUNDACION VALLE DEL LILI | P39: =VLOOKUP(B39,'NIVEL ENERO'!A:D,3,0) -> 0.36386528 | Q39: =VLOOKUP(B39,'NIVEL ENERO'!A:D,4,0) -> 223252.68 | R39: =+PROPER(C39&" "&D39) -> Nino Motato Hugo Fernando | S39: =+YEARFRAC(L39,$S$1) -> 4.0666667 | T39: =+YEARFRAC(M39,$S$1) -> 19.269444 | U39: =+$I39 -> 2462396 | V39: =+PROPER(F39) -> Casado(A)
B40: 14839121 | C40: URIBE PAZ | D40: HARVIN RICARDO | E40: CALI | F40: Casado(a) | G40: 1918500 | H40: 1864687 | I40: 0 | J40: 44 | K40: 1 | L40: 45051 | M40: 44378 | N40: 0 | O40: FUNDACION VALLE DEL LILI | P40: =VLOOKUP(B40,'NIVEL ENERO'!A:D,3,0) -> 0.49502686 | Q40: =VLOOKUP(B40,'NIVEL ENERO'!A:D,4,0) -> -342712 | R40: =+PROPER(C40&" "&D40) -> Uribe Paz Harvin Ricardo | S40: =+YEARFRAC(L40,$S$1) -> 3.0194444 | T40: =+YEARFRAC(M40,$S$1) -> 4.8638889 | U40: =+$I40 -> 0 | V40: =+PROPER(F40) -> Casado(A)
B41: 14839579 | C41: TROCHEZ DELGADO | D41: JHON JAIRO | E41: CALI | F41: Union libre | G41: 4383200 | H41: 12412153 | I41: 0 | J41: 44 | K41: 1 | L41: 38687 | M41: 38306 | N41: 2 | O41: FUNDACION VALLE DEL LILI | P41: =VLOOKUP(B41,'NIVEL ENERO'!A:D,3,0) -> 0.10864498 | Q41: =VLOOKUP(B41,'NIVEL ENERO'!A:D,4,0) -> 1497029.2 | R41: =+PROPER(C41&" "&D41) -> Trochez Delgado Jhon Jairo | S41: =+YEARFRAC(L41,$S$1) -> 20.447222 | T41: =+YEARFRAC(M41,$S$1) -> 21.491667 | U41: =+$I41 -> 0 | V41: =+PROPER(F41) -> Union Libre
B42: 14893690 | C42: VIVEROS DARAVINA | D42: JAIR SIDNEY | E42: CALI | F42: Casado(a) | G42: 10237200 | H42: 2405675 | J42: 54 | K42: 1 | L42: 44939 | M42: 44837 | N42: 0 | O42: FUNDACION VALLE DEL LILI | P42: =VLOOKUP(B42,'NIVEL ENERO'!A:D,3,0) -> 0.14624751 | Q42: =VLOOKUP(B42,'NIVEL ENERO'!A:D,4,0) -> 2802459 | R42: =+PROPER(C42&" "&D42) -> Viveros Daravina Jair Sidney | S42: =+YEARFRAC(L42,$S$1) -> 3.3305556 | T42: =+YEARFRAC(M42,$S$1) -> 3.6083333 | U42: =+$I42 -> 0 | V42: =+PROPER(F42) -> Casado(A)
B43: 14894421 | C43: GOMEZ | D43: JOSE OLMES | E43: CALI | F43: Soltero(a) | G43: 1400000 | H43: 3462432 | I43: 424260 | J43: 55 | K43: 2 | L43: 43595 | M43: 42614 | N43: 2 | O43: ASOCIACION VOLUNTARIADO FCVL | P43: =VLOOKUP(B43,'NIVEL ENERO'!A:D,3,0) -> #N/A | Q43: =VLOOKUP(B43,'NIVEL ENERO'!A:D,4,0) -> #N/A | R43: =+PROPER(C43&" "&D43) -> Gomez Jose Olmes | S43: =+YEARFRAC(L43,$S$1) -> 7.0055556 | T43: =+YEARFRAC(M43,$S$1) -> 9.6972222 | U43: =+$I43 -> 424260 | V43: =+PROPER(F43) -> Soltero(A)
B44: 16282233 | C44: GONZALEZ OLIVEROS | D44: LUIS FERNANDO | E44: CALI | F44: Soltero(a) | G44: 8245400 | H44: 3713126 | I44: 0 | J44: 57 | K44: 1 | L44: 43299 | M44: 40589 | N44: 1 | O44: FUNDACION VALLE DEL LILI | P44: =VLOOKUP(B44,'NIVEL ENERO'!A:D,3,0) -> 0.16623281 | Q44: =VLOOKUP(B44,'NIVEL ENERO'!A:D,4,0) -> 2115251 | R44: =+PROPER(C44&" "&D44) -> Gonzalez Oliveros Luis Fernando | S44: =+YEARFRAC(L44,$S$1) -> 7.8166667 | T44: =+YEARFRAC(M44,$S$1) -> 15.241667 | U44: =+$I44 -> 0 | V44: =+PROPER(F44) -> Soltero(A)
B45: 16283520 | C45: OIDOR LOZANO | D45: GINO HUMBERTO | E45: CALI | F45: Casado(a) | G45: 6247700 | H45: 6549188 | I45: 0 | J45: 56 | K45: 1 | L45: 44757 | M45: 39576 | N45: 1 | O45: FUNDACION VALLE DEL LILI | P45: =VLOOKUP(B45,'NIVEL ENERO'!A:D,3,0) -> 0.14245824 | Q45: =VLOOKUP(B45,'NIVEL ENERO'!A:D,4,0) -> 2165070.6 | R45: =+PROPER(C45&" "&D45) -> Oidor Lozano Gino Humberto | S45: =+YEARFRAC(L45,$S$1) -> 3.825 | T45: =+YEARFRAC(M45,$S$1) -> 18.011111 | U45: =+$I45 -> 0 | V45: =+PROPER(F45) -> Casado(A)
B46: 16285415 | C46: RAMIREZ MARIN | D46: DIEGO HERNAN | E46: CALI | F46: Casado(a) | G46: 2893800 | H46: 1910716 | I46: 1731232 | J46: 45 | K46: 1 | L46: 44642 | M46: 44105 | N46: 5 | O46: FUNDACION VALLE DEL LILI | P46: =VLOOKUP(B46,'NIVEL ENERO'!A:D,3,0) -> 0.40166014 | Q46: =VLOOKUP(B46,'NIVEL ENERO'!A:D,4,0) -> 55072.44 | R46: =+PROPER(C46&" "&D46) -> Ramirez Marin Diego Hernan | S46: =+YEARFRAC(L46,$S$1) -> 4.1388889 | T46: =+YEARFRAC(M46,$S$1) -> 5.6138889 | U46: =+$I46 -> 1731232 | V46: =+PROPER(F46) -> Casado(A)
B47: 16285644 | C47: BARRAGAN CALDERON | D47: DIEGO MAURICIO | E47: CALI | F47: Union libre | G47: 9087800 | H47: 1607671 | I47: 0 | J47: 45 | K47: 3 | L47: 44854 | M47: 44124 | N47: 0 | O47: FUNDACION VALLE DEL LILI | P47: =VLOOKUP(B47,'NIVEL ENERO'!A:D,3,0) -> 0.13385297 | Q47: =VLOOKUP(B47,'NIVEL ENERO'!A:D,4,0) -> 2778521.1 | R47: =+PROPER(C47&" "&D47) -> Barragan Calderon Diego Mauricio | S47: =+YEARFRAC(L47,$S$1) -> 3.5611111 | T47: =+YEARFRAC(M47,$S$1) -> 5.5611111 | U47: =+$I47 -> 0 | V47: =+PROPER(F47) -> Union Libre
B48: 16375423 | C48: ZAPATA VELASCO | D48: HERNAN ALONSO | E48: CALI | F48: Casado(a) | G48: 2089800 | H48: 3856554 | I48: 0 | J48: 40 | K48: 1 | L48: 44669 | M48: 42444 | N48: 4 | O48: FUNDACION VALLE DEL LILI | P48: =VLOOKUP(B48,'NIVEL ENERO'!A:D,3,0) -> 0.37958856 | Q48: =VLOOKUP(B48,'NIVEL ENERO'!A:D,4,0) -> 106727.52 | R48: =+PROPER(C48&" "&D48) -> Zapata Velasco Hernan Alonso | S48: =+YEARFRAC(L48,$S$1) -> 4.0666667 | T48: =+YEARFRAC(M48,$S$1) -> 10.158333 | U48: =+$I48 -> 0 | V48: =+PROPER(F48) -> Casado(A)
B49: 16377725 | C49: VEGA MOSQUERA | D49: ANDRES MAURICIO | E49: CALI | F49: Soltero(a) | G49: 8245400 | H49: 7462269 | I49: 54516477 | J49: 40 | K49: 2 | L49: 40130 | M49: 40120 | N49: 3 | O49: FUNDACION VALLE DEL LILI | P49: =VLOOKUP(B49,'NIVEL ENERO'!A:D,3,0) -> 0.32920191 | Q49: =VLOOKUP(B49,'NIVEL ENERO'!A:D,4,0) -> 760755.9 | R49: =+PROPER(C49&" "&D49) -> Vega Mosquera Andres Mauricio | S49: =+YEARFRAC(L49,$S$1) -> 16.497222 | T49: =+YEARFRAC(M49,$S$1) -> 16.525 | U49: =+$I49 -> 54516477 | V49: =+PROPER(F49) -> Soltero(A)
B50: 16379970 | C50: CAICEDO QUINTERO | D50: LEANDRO | E50: CALI | F50: Union libre | G50: 2893800 | H50: 1075381 | I50: 0 | J50: 39 | K50: 4 | L50: 45142 | M50: 41417 | N50: 5 | O50: FUNDACION VALLE DEL LILI | P50: =VLOOKUP(B50,'NIVEL ENERO'!A:D,3,0) -> 0.26736522 | Q50: =VLOOKUP(B50,'NIVEL ENERO'!A:D,4,0) -> 551702.08 | R50: =+PROPER(C50&" "&D50) -> Caicedo Quintero Leandro | S50: =+YEARFRAC(L50,$S$1) -> 2.7722222 | T50: =+YEARFRAC(M50,$S$1) -> 12.969444 | U50: =+$I50 -> 0 | V50: =+PROPER(F50) -> Union Libre
B51: 16457828 | C51: MORALES SANCHEZ | D51: MIGUEL ANGEL | E51: CALI | F51: Union libre | G51: 2893800 | H51: 300000 | I51: 0 | J51: 46 | K51: 2 | L51: 45587 | M51: 36601 | N51: 3 | O51: FUNDACION VALLE DEL LILI | P51: =VLOOKUP(B51,'NIVEL ENERO'!A:D,3,0) -> 0.15510544 | Q51: =VLOOKUP(B51,'NIVEL ENERO'!A:D,4,0) -> 1084615.6 | R51: =+PROPER(C51&" "&D51) -> Morales Sanchez Miguel Angel | S51: =+YEARFRAC(L51,$S$1) -> 1.5555556 | T51: =+YEARFRAC(M51,$S$1) -> 26.155556 | U51: =+$I51 -> 0 | V51: =+PROPER(F51) -> Union Libre
B52: 16537560 | C52: CARDOZO | D52: LUIS FELIPE | E52: CALI | F52: Soltero(a) | G52: 2255900 | H52: 2053147 | I52: 3894249 | J52: 42 | K52: 2 | L52: 44551 | M52: 44326 | N52: 3 | O52: FUNDACION VALLE DEL LILI | P52: =VLOOKUP(B52,'NIVEL ENERO'!A:D,3,0) -> 0.35036802 | Q52: =VLOOKUP(B52,'NIVEL ENERO'!A:D,4,0) -> 198762.78 | R52: =+PROPER(C52&" "&D52) -> Cardozo Luis Felipe | S52: =+YEARFRAC(L52,$S$1) -> 4.3916667 | T52: =+YEARFRAC(M52,$S$1) -> 5.0055556 | U52: =+$I52 -> 3894249 | V52: =+PROPER(F52) -> Soltero(A)
B53: 16699405 | C53: DELGADO VILLEGAS | D53: CARLOS ALBERTO | E53: CALI | F53: Casado(a) | G53: 2017100 | H53: 4868171 | I53: 8693235 | J53: 60 | K53: 4 | L53: 42192 | M53: 30180 | N53: 3 | O53: FUNDACION VALLE DEL LILI | P53: =VLOOKUP(B53,'NIVEL ENERO'!A:D,3,0) -> 0.33811759 | Q53: =VLOOKUP(B53,'NIVEL ENERO'!A:D,4,0) -> 165165 | R53: =+PROPER(C53&" "&D53) -> Delgado Villegas Carlos Alberto | S53: =+YEARFRAC(L53,$S$1) -> 10.847222 | T53: =+YEARFRAC(M53,$S$1) -> 43.736111 | U53: =+$I53 -> 8693235 | V53: =+PROPER(F53) -> Casado(A)
B54: 16701228 | C54: CARDENAS VARELA | D54: LUIS EDUARDO | E54: CALI | F54: Union libre | G54: 2600900 | H54: 4484998 | I54: 0 | J54: 60 | K54: 1 | L54: 44417 | M54: 35548 | N54: 3 | O54: FUNDACION VALLE DEL LILI | P54: =VLOOKUP(B54,'NIVEL ENERO'!A:D,3,0) -> 0.15367417 | Q54: =VLOOKUP(B54,'NIVEL ENERO'!A:D,4,0) -> 917559.14 | R54: =+PROPER(C54&" "&D54) -> Cardenas Varela Luis Eduardo | S54: =+YEARFRAC(L54,$S$1) -> 4.7583333 | T54: =+YEARFRAC(M54,$S$1) -> 29.038889 | U54: =+$I54 -> 0 | V54: =+PROPER(F54) -> Union Libre
... B77: 16849715 | C77: ANACONA ANGULO | D77: LUIS ALBERTO | E77: CALI | F77: Union libre | G77: 4234800 | H77: 2379426 | I77: 179747 | J77: 40 | K77: 3 | L77: 44328 | M77: 40238 | N77: 4 | O77: FUNDACION VALLE DEL LILI | P77: =VLOOKUP(B77,'NIVEL ENERO'!A:D,3,0) -> 0.15236186 | Q77: =VLOOKUP(B77,'NIVEL ENERO'!A:D,4,0) -> 1133394 | R77: =+PROPER(C77&" "&D77) -> Anacona Angulo Luis Alberto | S77: =+YEARFRAC(L77,$S$1) -> 5 | T77: =+YEARFRAC(M77,$S$1) -> 16.197222 | U77: =+$I77 -> 179747 | V77: =+PROPER(F77) -> Union Libre
B78: 16865656 | C78: ALMESA IBARRA | D78: JEISSON | E78: CALI | F78: Casado(a) | G78: 1880800 | H78: 130000 | J78: 41 | K78: 1 | L78: 45615 | M78: 41133 | N78: 0 | O78: FUNDACION VALLE DEL LILI | P78: =VLOOKUP(B78,'NIVEL ENERO'!A:D,3,0) -> 0.35582326 | Q78: =VLOOKUP(B78,'NIVEL ENERO'!A:D,4,0) -> 142745.14 | R78: =+PROPER(C78&" "&D78) -> Almesa Ibarra Jeisson | S78: =+YEARFRAC(L78,$S$1) -> 1.4805556 | T78: =+YEARFRAC(M78,$S$1) -> 13.75 | U78: =+$I78 -> 0 | V78: =+PROPER(F78) -> Casado(A)
B79: 16889110 | C79: OPANCE COLLO | D79: MILTON LIDER | E79: CALI | F79: Separado(a) | G79: 1918500 | H79: 2425387 | I79: 3026858 | J79: 51 | K79: 4 | L79: 44305 | M79: 44105 | N79: 2 | O79: FUNDACION VALLE DEL LILI | P79: =VLOOKUP(B79,'NIVEL ENERO'!A:D,3,0) -> 0.41506837 | Q79: =VLOOKUP(B79,'NIVEL ENERO'!A:D,4,0) -> 22527 | R79: =+PROPER(C79&" "&D79) -> Opance Collo Milton Lider | S79: =+YEARFRAC(L79,$S$1) -> 5.0638889 | T79: =+YEARFRAC(M79,$S$1) -> 5.6138889 | U79: =+$I79 -> 3026858 | V79: =+PROPER(F79) -> Separado(A)
B80: 16893872 | C80: DAVILA LEDESMA | D80: HUGO FERNANDO | E80: CALI | F80: Soltero(a) | G80: 6500000 | H80: 1045473 | I80: 8458337 | J80: 44 | K80: 1 | L80: 45044 | M80: 45033 | N80: 0 | O80: COOPVALILI | P80: =VLOOKUP(B80,'NIVEL ENERO'!A:D,3,0) -> #N/A | Q80: =VLOOKUP(B80,'NIVEL ENERO'!A:D,4,0) -> #N/A | R80: =+PROPER(C80&" "&D80) -> Davila Ledesma Hugo Fernando | S80: =+YEARFRAC(L80,$S$1) -> 3.0388889 | T80: =+YEARFRAC(M80,$S$1) -> 3.0694444 | U80: =+$I80 -> 8458337 | V80: =+PROPER(F80) -> Soltero(A)
B81: 16896487 | C81: PARRA LOPEZ | D81: GUSTAVO ANDRES | E81: CALI | F81: Casado(a) | G81: 1755600 | H81: 3331872 | I81: 5842427 | J81: 40 | K81: 2 | L81: 43564 | M81: 42325 | N81: 2 | O81: FUNDACION VALLE DEL LILI | P81: =VLOOKUP(B81,'NIVEL ENERO'!A:D,3,0) -> 0.48175627 | Q81: =VLOOKUP(B81,'NIVEL ENERO'!A:D,4,0) -> -282225 | R81: =+PROPER(C81&" "&D81) -> Parra Lopez Gustavo Andres | S81: =+YEARFRAC(L81,$S$1) -> 7.0916667 | T81: =+YEARFRAC(M81,$S$1) -> 10.486111 | U81: =+$I81 -> 5842427 | V81: =+PROPER(F81) -> Casado(A)
B82: 16915378 | C82: HERRERA VILLALBA | D82: CHARLES ROWER | E82: CALI | F82: Soltero(a) | G82: 6946500 | H82: 9637648 | I82: 2549106 | J82: 45 | K82: 2 | L82: 41736 | M82: 37057 | N82: 2 | O82: FUNDACION VALLE DEL LILI | P82: =VLOOKUP(B82,'NIVEL ENERO'!A:D,3,0) -> 0.39254254 | Q82: =VLOOKUP(B82,'NIVEL ENERO'!A:D,4,0) -> 207345 | R82: =+PROPER(C82&" "&D82) -> Herrera Villalba Charles Rower | S82: =+YEARFRAC(L82,$S$1) -> 12.097222 | T82: =+YEARFRAC(M82,$S$1) -> 24.908333 | U82: =+$I82 -> 2549106 | V82: =+PROPER(F82) -> Soltero(A)
B83: 16917362 | C83: SERNA ESPINOSA | D83: FABIAN ANDRES | E83: FLORIDA | F83: Casado(a) | G83: 4870200 | H83: 4122930 | J83: 44 | K83: 1 | L83: 44396 | M83: 44105 | N83: 4 | O83: FUNDACION VALLE DEL LILI | P83: =VLOOKUP(B83,'NIVEL ENERO'!A:D,3,0) -> 0.11945951 | Q83: =VLOOKUP(B83,'NIVEL ENERO'!A:D,4,0) -> 1904709 | R83: =+PROPER(C83&" "&D83) -> Serna Espinosa Fabian Andres | S83: =+YEARFRAC(L83,$S$1) -> 4.8138889 | T83: =+YEARFRAC(M83,$S$1) -> 5.6138889 | U83: =+$I83 -> 0 | V83: =+PROPER(F83) -> Casado(A)
B84: 16918531 | C84: CORREA MURILLO | D84: CESAR AUGUSTO | E84: CALI | F84: Soltero(a) | G84: 2600900 | H84: 650225 | I84: 345523 | J84: 43 | K84: 2 | L84: 45518 | M84: 40260 | N84: 2 | O84: FUNDACION VALLE DEL LILI | P84: =VLOOKUP(B84,'NIVEL ENERO'!A:D,3,0) -> 0.47293168 | Q84: =VLOOKUP(B84,'NIVEL ENERO'!A:D,4,0) -> -137670 | R84: =+PROPER(C84&" "&D84) -> Correa Murillo Cesar Augusto | S84: =+YEARFRAC(L84,$S$1) -> 1.7444444 | T84: =+YEARFRAC(M84,$S$1) -> 16.136111 | U84: =+$I84 -> 345523 | V84: =+PROPER(F84) -> Soltero(A)
B85: 16918596 | C85: TABORDA VALENCIA | D85: PAULO ANDRES | E85: CALI | F85: Casado(a) | G85: 2893800 | H85: 4785887 | I85: 1274859 | J85: 43 | K85: 2 | L85: 42930 | M85: 38119 | N85: 5 | O85: FUNDACION VALLE DEL LILI | P85: =VLOOKUP(B85,'NIVEL ENERO'!A:D,3,0) -> 0.38221569 | Q85: =VLOOKUP(B85,'NIVEL ENERO'!A:D,4,0) -> 106910.48 | R85: =+PROPER(C85&" "&D85) -> Taborda Valencia Paulo Andres | S85: =+YEARFRAC(L85,$S$1) -> 8.8277778 | T85: =+YEARFRAC(M85,$S$1) -> 22 | U85: =+$I85 -> 1274859 | V85: =+PROPER(F85) -> Casado(A)
B86: 16918654 | C86: DIAZ SALGADO | D86: JESUS ALVENIS | E86: CALI | F86: Union libre | G86: 5812800 | H86: 1000000 | I86: 0 | J86: 43 | K86: 1 | L86: 38735 | M86: 36395 | N86: 0 | O86: FUNDACION VALLE DEL LILI | P86: =VLOOKUP(B86,'NIVEL ENERO'!A:D,3,0) -> 0.11362321 | Q86: =VLOOKUP(B86,'NIVEL ENERO'!A:D,4,0) -> 1780907 | R86: =+PROPER(C86&" "&D86) -> Diaz Salgado Jesus Alvenis | S86: =+YEARFRAC(L86,$S$1) -> 20.316667 | T86: =+YEARFRAC(M86,$S$1) -> 26.719444 | U86: =+$I86 -> 0 | V86: =+PROPER(F86) -> Union Libre
B87: 16918740 | C87: CALLE CAMACHO | D87: DEYBI | E87: CALI | F87: Viudo(a) | G87: 2916600 | H87: 2053147 | I87: 73917 | J87: 44 | K87: 3 | L87: 44550 | M87: 40736 | N87: 3 | O87: FUNDACION VALLE DEL LILI | P87: =VLOOKUP(B87,'NIVEL ENERO'!A:D,3,0) -> 0.12327269 | Q87: =VLOOKUP(B87,'NIVEL ENERO'!A:D,4,0) -> 1036640.6 | R87: =+PROPER(C87&" "&D87) -> Calle Camacho Deybi | S87: =+YEARFRAC(L87,$S$1) -> 4.3944444 | T87: =+YEARFRAC(M87,$S$1) -> 14.833333 | U87: =+$I87 -> 73917 | V87: =+PROPER(F87) -> Viudo(A)
B88: 16918838 | C88: JAVELA HERRERA | D88: JULIAN | E88: CALI | F88: Soltero(a) | G88: 2893800 | H88: 9876915 | I88: 0 | J88: 43 | K88: 1 | L88: 40422 | M88: 40406 | N88: 1 | O88: FUNDACION VALLE DEL LILI | P88: =VLOOKUP(B88,'NIVEL ENERO'!A:D,3,0) -> 0.36060025 | Q88: =VLOOKUP(B88,'NIVEL ENERO'!A:D,4,0) -> 171891 | R88: =+PROPER(C88&" "&D88) -> Javela Herrera Julian | S88: =+YEARFRAC(L88,$S$1) -> 15.697222 | T88: =+YEARFRAC(M88,$S$1) -> 15.738889 | U88: =+$I88 -> 0 | V88: =+PROPER(F88) -> Soltero(A)
B89: 16926618 | C89: FRAGA RECALDE | D89: NELSON ANDRES | E89: CALI | F89: Soltero(a) | G89: 2089800 | H89: 4544182 | I89: 11610614 | J89: 44 | K89: 1 | L89: 42710 | M89: 38888 | N89: 3 | O89: FUNDACION VALLE DEL LILI | P89: =VLOOKUP(B89,'NIVEL ENERO'!A:D,3,0) -> 0.41662462 | Q89: =VLOOKUP(B89,'NIVEL ENERO'!A:D,4,0) -> 8746.28 | R89: =+PROPER(C89&" "&D89) -> Fraga Recalde Nelson Andres | S89: =+YEARFRAC(L89,$S$1) -> 9.4333333 | T89: =+YEARFRAC(M89,$S$1) -> 19.894444 | U89: =+$I89 -> 11610614 | V89: =+PROPER(F89) -> Soltero(A)
B90: 16930766 | C90: URREGO LOTERO | D90: EDINSON ANDRES | E90: CALI | F90: Soltero(a) | G90: 2893800 | H90: 8955362 | I90: 22389700 | J90: 46 | K90: 4 | L90: 40490 | M90: 40261 | N90: 2 | O90: FUNDACION VALLE DEL LILI | P90: =VLOOKUP(B90,'NIVEL ENERO'!A:D,3,0) -> 0.39589725 | Q90: =VLOOKUP(B90,'NIVEL ENERO'!A:D,4,0) -> 81777.64 | R90: =+PROPER(C90&" "&D90) -> Urrego Lotero Edinson Andres | S90: =+YEARFRAC(L90,$S$1) -> 15.511111 | T90: =+YEARFRAC(M90,$S$1) -> 16.133333 | U90: =+$I90 -> 22389700 | V90: =+PROPER(F90) -> Soltero(A)
B91: 16934229 | C91: SERNA GIRALDO | D91: MAURICIO | E91: CALI | F91: Casado(a) | G91: 7114600 | H91: 800000 | I91: 0 | J91: 43 | K91: 1 | L91: 45555 | M91: 42009 | N91: 1 | O91: FUNDACION VALLE DEL LILI | P91: =VLOOKUP(B91,'NIVEL ENERO'!A:D,3,0) -> 0.33951621 | Q91: =VLOOKUP(B91,'NIVEL ENERO'!A:D,4,0) -> 572610 | R91: =+PROPER(C91&" "&D91) -> Serna Giraldo Mauricio | S91: =+YEARFRAC(L91,$S$1) -> 1.6444444 | T91: =+YEARFRAC(M91,$S$1) -> 11.352778 | U91: =+$I91 -> 0 | V91: =+PROPER(F91) -> Casado(A)
B92: 16934523 | C92: SILVA LOZANO | D92: JEFFERSON | E92: CALI | F92: Soltero(a) | G92: 2893800 | H92: 100000 | J92: 43 | K92: 2 | L92: 45643 | M92: 44805 | N92: 0 | O92: FUNDACION VALLE DEL LILI | P92: =VLOOKUP(B92,'NIVEL ENERO'!A:D,3,0) -> #N/A | Q92: =VLOOKUP(B92,'NIVEL ENERO'!A:D,4,0) -> #N/A | R92: =+PROPER(C92&" "&D92) -> Silva Lozano Jefferson | S92: =+YEARFRAC(L92,$S$1) -> 1.4027778 | T92: =+YEARFRAC(M92,$S$1) -> 3.6972222 | U92: =+$I92 -> 0 | V92: =+PROPER(F92) -> Soltero(A)
B93: 16940638 | C93: ISAZA VALENCIA | D93: HERNAN ALONSO | E93: CALI | F93: Union libre | G93: 2320800 | H93: 2946524 | I93: 3822856 | J93: 43 | K93: 4 | L93: 43928 | M93: 38861 | N93: 3 | O93: FUNDACION VALLE DEL LILI | P93: =VLOOKUP(B93,'NIVEL ENERO'!A:D,3,0) -> 0.21077275 | Q93: =VLOOKUP(B93,'NIVEL ENERO'!A:D,4,0) -> 679159.26 | R93: =+PROPER(C93&" "&D93) -> Isaza Valencia Hernan Alonso | S93: =+YEARFRAC(L93,$S$1) -> 6.0972222 | T93: =+YEARFRAC(M93,$S$1) -> 19.966667 | U93: =+$I93 -> 3822856 | V93: =+PROPER(F93) -> Union Libre
B94: 16942315 | C94: LONDONO HERNANDEZ | D94: ROBERTH ANDRES | E94: CALI | F94: Casado(a) | G94: 13588800 | H94: 1200000 | I94: 0 | J94: 43 | K94: 6 | L94: 45222 | M94: 42522 | N94: 2 | O94: FUNDACION VALLE DEL LILI | P94: =VLOOKUP(B94,'NIVEL ENERO'!A:D,3,0) -> 0.17526191 | Q94: =VLOOKUP(B94,'NIVEL ENERO'!A:D,4,0) -> 3325697 | R94: =+PROPER(C94&" "&D94) -> Londono Hernandez Roberth Andres | S94: =+YEARFRAC(L94,$S$1) -> 2.5527778 | T94: =+YEARFRAC(M94,$S$1) -> 9.9472222 | U94: =+$I94 -> 0 | V94: =+PROPER(F94) -> Casado(A)
B95: 16945354 | C95: LONDONO LOPEZ | D95: EDWIN | E95: CALI | F95: Casado(a) | G95: 1625000 | H95: 650000 | I95: 802578 | J95: 43 | K95: 2 | L95: 45369 | M95: 45323 | N95: 0 | O95: FUNDACION VALLE DEL LILI | P95: =VLOOKUP(B95,'NIVEL ENERO'!A:D,3,0) -> 0.43398484 | Q95: =VLOOKUP(B95,'NIVEL ENERO'!A:D,4,0) -> -54108 | R95: =+PROPER(C95&" "&D95) -> Londono Lopez Edwin | S95: =+YEARFRAC(L95,$S$1) -> 2.15 | T95: =+YEARFRAC(M95,$S$1) -> 2.2805556 | U95: =+$I95 -> 802578 | V95: =+PROPER(F95) -> Casado(A)
B96: 16985476 | C96: RODRIGUEZ DIAZ | D96: DIEGO FERNANDO | E96: CALI | F96: Union libre | G96: 2681200 | H96: 6327802 | I96: 2546705 | J96: 59 | K96: 1 | L96: 44273 | M96: 40192 | N96: 1 | O96: FUNDACION VALLE DEL LILI | P96: =VLOOKUP(B96,'NIVEL ENERO'!A:D,3,0) -> 0.39593202 | Q96: =VLOOKUP(B96,'NIVEL ENERO'!A:D,4,0) -> 73696.36 | R96: =+PROPER(C96&" "&D96) -> Rodriguez Diaz Diego Fernando | S96: =+YEARFRAC(L96,$S$1) -> 5.15 | T96: =+YEARFRAC(M96,$S$1) -> 16.327778 | U96: =+$I96 -> 2546705 | V96: =+PROPER(F96) -> Union Libre
B97: 19601683 | C97: CANTILLO DUEÑAS | D97: ELIECER ANTONIO | E97: CALI | F97: Soltero(a) | G97: 5224200 | H97: 1015322 | I97: 1335198 | J97: 41 | K97: 1 | L97: 45191 | M97: 42722 | N97: 1 | O97: FUNDACION VALLE DEL LILI | P97: =VLOOKUP(B97,'NIVEL ENERO'!A:D,3,0) -> 0.12454579 | Q97: =VLOOKUP(B97,'NIVEL ENERO'!A:D,4,0) -> 1892840.2 | R97: =+PROPER(C97&" "&D97) -> Cantillo Dueñas Eliecer Antonio | S97: =+YEARFRAC(L97,$S$1) -> 2.6388889 | T97: =+YEARFRAC(M97,$S$1) -> 9.4 | U97: =+$I97 -> 1335198 | V97: =+PROPER(F97) -> Soltero(A)
B98: 22462719 | C98: PELAEZ HURTADO | D98: BLANCA HELENA | E98: CALI | F98: Casado(a) | G98: 9087800 | H98: 2506690 | I98: 0 | J98: 47 | K98: 2 | L98: 44908 | M98: 41610 | N98: 0 | O98: FUNDACION VALLE DEL LILI | P98: =VLOOKUP(B98,'NIVEL ENERO'!A:D,3,0) -> 0.43443381 | Q98: =VLOOKUP(B98,'NIVEL ENERO'!A:D,4,0) -> -131171.58 | R98: =+PROPER(C98&" "&D98) -> Pelaez Hurtado Blanca Helena | S98: =+YEARFRAC(L98,$S$1) -> 3.4138889 | T98: =+YEARFRAC(M98,$S$1) -> 12.444444 | U98: =+$I98 -> 0 | V98: =+PROPER(F98) -> Casado(A)
B99: 22665545 | C99: RODRIGUEZ GONZALEZ | D99: ISAGLEIDYS DEL AMPARO | E99: CALI | F99: Union libre | G99: 5842800 | H99: 2314776 | I99: 373933 | J99: 43 | K99: 1 | L99: 44390 | M99: 42740 | N99: 2 | O99: FUNDACION VALLE DEL LILI | P99: =VLOOKUP(B99,'NIVEL ENERO'!A:D,3,0) -> 0.12161549 | Q99: =VLOOKUP(B99,'NIVEL ENERO'!A:D,4,0) -> 1743401 | R99: =+PROPER(C99&" "&D99) -> Rodriguez Gonzalez Isagleidys Del Amparo | S99: =+YEARFRAC(L99,$S$1) -> 4.8305556 | T99: =+YEARFRAC(M99,$S$1) -> 9.3527778 | U99: =+$I99 -> 373933 | V99: =+PROPER(F99) -> Union Libre
B100: 22734707 | C100: LOBO HERNANDEZ | D100: KELLY JOHANA | E100: CALI | F100: Soltero(a) | G100: 7000000 | H100: 2500000 | I100: 41555232 | J100: 43 | K100: 2 | L100: 45352 | M100: 43670 | N100: 0 | O100: FUNDACION VALLE DEL LILI - HONORARIOS | P100: =VLOOKUP(B100,'NIVEL ENERO'!A:D,3,0) -> #N/A | Q100: =VLOOKUP(B100,'NIVEL ENERO'!A:D,4,0) -> #N/A | R100: =+PROPER(C100&" "&D100) -> Lobo Hernandez Kelly Johana | S100: =+YEARFRAC(L100,$S$1) -> 2.1972222 | T100: =+YEARFRAC(M100,$S$1) -> 6.8 | U100: =+$I100 -> 41555232 | V100: =+PROPER(F100) -> Soltero(A)
B101: 24331999 | C101: NAVARRO ZULUAGA | D101: YULIETH LORENA | E101: CALI | F101: Casado(a) | G101: 6225200 | H101: 2391078 | I101: 0 | J101: 43 | K101: 1 | L101: 44579 | M101: 38202 | N101: 3 | O101: FUNDACION VALLE DEL LILI | P101: =VLOOKUP(B101,'NIVEL ENERO'!A:D,3,0) -> 0.17455487 | Q101: =VLOOKUP(B101,'NIVEL ENERO'!A:D,4,0) -> 1527945 | R101: =+PROPER(C101&" "&D101) -> Navarro Zuluaga Yulieth Lorena | S101: =+YEARFRAC(L101,$S$1) -> 4.3166667 | T101: =+YEARFRAC(M101,$S$1) -> 21.775 | U101: =+$I101 -> 0 | V101: =+PROPER(F101) -> Casado(A)
B102: 24338540 | C102: VILLADA ALVAREZ | D102: MIYERLAY | E102: CALI | F102: Soltero(a) | G102: 6225200 | H102: 5578305 | J102: 39 | K102: 1 | L102: 44552 | M102: 42506 | N102: 2 | O102: FUNDACION VALLE DEL LILI | P102: =VLOOKUP(B102,'NIVEL ENERO'!A:D,3,0) -> 0.34780393 | Q102: =VLOOKUP(B102,'NIVEL ENERO'!A:D,4,0) -> 449435 | R102: =+PROPER(C102&" "&D102) -> Villada Alvarez Miyerlay | S102: =+YEARFRAC(L102,$S$1) -> 4.3888889 | T102: =+YEARFRAC(M102,$S$1) -> 9.9888889 | U102: =+$I102 -> 0 | V102: =+PROPER(F102) -> Soltero(A)
B103: 24340972 | C103: ZULUAGA RAMIREZ | D103: SANDRA MILENA | E103: CALI | F103: Casado(a) | G103: 2600900 | H103: 1557164 | I103: 181063 | J103: 43 | K103: 6 | L103: 44846 | M103: 44105 | N103: 3 | O103: FUNDACION VALLE DEL LILI | P103: =VLOOKUP(B103,'NIVEL ENERO'!A:D,3,0) -> 0.32018867 | Q103: =VLOOKUP(B103,'NIVEL ENERO'!A:D,4,0) -> 532053.1 | R103: =+PROPER(C103&" "&D103) -> Zuluaga Ramirez Sandra Milena | S103: =+YEARFRAC(L103,$S$1) -> 3.5833333 | T103: =+YEARFRAC(M103,$S$1) -> 5.6138889 | U103: =+$I103 -> 181063 | V103: =+PROPER(F103) -> Casado(A)
B104: 24341885 | C104: ZAPATA ZAPATA | D104: LUZ ADRIANA | E104: CALI | F104: Union libre | G104: 5842800 | H104: 2043886 | I104: 1440846 | J104: 43 | K104: 1 | L104: 44669 | M104: 44094 | N104: 2 | O104: FUNDACION VALLE DEL LILI | P104: =VLOOKUP(B104,'NIVEL ENERO'!A:D,3,0) -> 0.20346221 | Q104: =VLOOKUP(B104,'NIVEL ENERO'!A:D,4,0) -> 1265187 | R104: =+PROPER(C104&" "&D104) -> Zapata Zapata Luz Adriana | S104: =+YEARFRAC(L104,$S$1) -> 4.0666667 | T104: =+YEARFRAC(M104,$S$1) -> 5.6444444 | U104: =+$I104 -> 1440846 | V104: =+PROPER(F104) -> Union Libre
B105: 24343891 | C105: ADARVE COBO | D105: SANDRA LILIANA | E105: CALI | F105: Soltero(a) | G105: 4870200 | H105: 3415825 | I105: 10076173 | J105: 39 | K105: 1 | L105: 44613 | M105: 44105 | N105: 0 | O105: FUNDACION VALLE DEL LILI | P105: =VLOOKUP(B105,'NIVEL ENERO'!A:D,3,0) -> 0.32225425 | Q105: =VLOOKUP(B105,'NIVEL ENERO'!A:D,4,0) -> 735379.24 | R105: =+PROPER(C105&" "&D105) -> Adarve Cobo Sandra Liliana | S105: =+YEARFRAC(L105,$S$1) -> 4.225 | T105: =+YEARFRAC(M105,$S$1) -> 5.6138889 | U105: =+$I105 -> 10076173 | V105: =+PROPER(F105) -> Soltero(A)
B106: 24348754 | C106: CARDONA MARTINEZ | D106: LUZ ADRIANA | E106: CALI | F106: Casado(a) | G106: 5418800 | H106: 18035465 | I106: 28540226 | J106: 44 | K106: 1 | L106: 39792 | M106: 37988 | N106: 5 | O106: FUNDACION VALLE DEL LILI | P106: =VLOOKUP(B106,'NIVEL ENERO'!A:D,3,0) -> 0.29228455 | Q106: =VLOOKUP(B106,'NIVEL ENERO'!A:D,4,0) -> 749897.08 | R106: =+PROPER(C106&" "&D106) -> Cardona Martinez Luz Adriana | S106: =+YEARFRAC(L106,$S$1) -> 17.422222 | T106: =+YEARFRAC(M106,$S$1) -> 22.361111 | U106: =+$I106 -> 28540226 | V106: =+PROPER(F106) -> Casado(A)
B107: 24527680 | C107: TAPASCO RAMIREZ | D107: GLORIA OLIVIA | E107: CALI | F107: Casado(a) | G107: 2000000 | H107: 2305675 | I107: 0 | J107: 57 | K107: 2 | L107: 44938 | M107: 35598 | N107: 2 | O107: ADMINISTRADOR COLOMBIANA DE PENSIONES | P107: =VLOOKUP(B107,'NIVEL ENERO'!A:D,3,0) -> #N/A | Q107: =VLOOKUP(B107,'NIVEL ENERO'!A:D,4,0) -> #N/A | R107: =+PROPER(C107&" "&D107) -> Tapasco Ramirez Gloria Olivia | S107: =+YEARFRAC(L107,$S$1) -> 3.3333333 | T107: =+YEARFRAC(M107,$S$1) -> 28.902778 | U107: =+$I107 -> 0 | V107: =+PROPER(F107) -> Casado(A)
B108: 24713592 | C108: ABRIL ACEVEDO | D108: MONICA ALEJANDRA | E108: CALI | F108: Union libre | G108: 2600900 | H108: 1121761 | J108: 44 | K108: 2 | L108: 45118 | M108: 44105 | N108: 0 | O108: FUNDACION VALLE DEL LILI | P108: =VLOOKUP(B108,'NIVEL ENERO'!A:D,3,0) -> 0.14620766 | Q108: =VLOOKUP(B108,'NIVEL ENERO'!A:D,4,0) -> 763760.06 | R108: =+PROPER(C108&" "&D108) -> Abril Acevedo Monica Alejandra | S108: =+YEARFRAC(L108,$S$1) -> 2.8361111 | T108: =+YEARFRAC(M108,$S$1) -> 5.6138889 | U108: =+$I108 -> 0 | V108: =+PROPER(F108) -> Union Libre
B109: 25273899 | C109: ARIAS CERON | D109: ELIANA MARCELA | E109: CALI | F109: Union libre | G109: 5418800 | H109: 4550039 | I109: 9260518 | J109: 47 | K109: 1 | L109: 45279 | M109: 45245 | N109: 0 | O109: FUNDACION VALLE DEL LILI | P109: =VLOOKUP(B109,'NIVEL ENERO'!A:D,3,0) -> 0.2333395 | Q109: =VLOOKUP(B109,'NIVEL ENERO'!A:D,4,0) -> 1061874.4 | R109: =+PROPER(C109&" "&D109) -> Arias Ceron Eliana Marcela | S109: =+YEARFRAC(L109,$S$1) -> 2.3972222 | T109: =+YEARFRAC(M109,$S$1) -> 2.4916667 | U109: =+$I109 -> 9260518 | V109: =+PROPER(F109) -> Union Libre
B110: 25277703 | C110: ILLERA PAEZ | D110: CLAUDIA MARITZA | E110: CALI | F110: Soltero(a) | G110: 5418800 | H110: 2405675 | I110: 4327866 | J110: 46 | K110: 1 | L110: 44939 | M110: 40238 | N110: 0 | O110: FUNDACION VALLE DEL LILI | P110: =VLOOKUP(B110,'NIVEL ENERO'!A:D,3,0) -> 0.35921307 | Q110: =VLOOKUP(B110,'NIVEL ENERO'!A:D,4,0) -> 448689.58 | R110: =+PROPER(C110&" "&D110) -> Illera Paez Claudia Maritza | S110: =+YEARFRAC(L110,$S$1) -> 3.3305556 | T110: =+YEARFRAC(M110,$S$1) -> 16.197222 | U110: =+$I110 -> 4327866 | V110: =+PROPER(F110) -> Soltero(A)
B111: 25283493 | C111: MILLAN CORREA | D111: DIANA LIZETH | E111: CALI | F111: Soltero(a) | G111: 5842800 | H111: 5840184 | I111: 0 | J111: 45 | K111: 1 | L111: 39797 | M111: 40007 | N111: 2 | O111: FUNDACION VALLE DEL LILI | P111: =VLOOKUP(B111,'NIVEL ENERO'!A:D,3,0) -> 0.13124342 | Q111: =VLOOKUP(B111,'NIVEL ENERO'!A:D,4,0) -> 1700141 | R111: =+PROPER(C111&" "&D111) -> Millan Correa Diana Lizeth | S111: =+YEARFRAC(L111,$S$1) -> 17.408333 | T111: =+YEARFRAC(M111,$S$1) -> 16.830556 | U111: =+$I111 -> 0 | V111: =+PROPER(F111) -> Soltero(A)
B112: 25287875 | C112: PEREZ SCHMALBACH | D112: SANDRA PATRICIA DEL CARMEN | E112: CALI | F112: Soltero(a) | G112: 7700000 | H112: 650000 | J112: 44 | K112: 1 | L112: 45352 | M112: 40791 | N112: 0 | O112: FUNDACION VALLE DEL LILI - HONORARIOS | P112: =VLOOKUP(B112,'NIVEL ENERO'!A:D,3,0) -> #N/A | Q112: =VLOOKUP(B112,'NIVEL ENERO'!A:D,4,0) -> #N/A | R112: =+PROPER(C112&" "&D112) -> Perez Schmalbach Sandra Patricia Del Carmen | S112: =+YEARFRAC(L112,$S$1) -> 2.1972222 | T112: =+YEARFRAC(M112,$S$1) -> 14.686111 | U112: =+$I112 -> 0 | V112: =+PROPER(F112) -> Soltero(A)
B113: 25331605 | C113: POPO CARABALI | D113: LUZ DELY | E113: CALI | F113: Union libre | G113: 2893800 | H113: 1506656 | I113: 116826 | J113: 44 | K113: 1 | L113: 44907 | M113: 44105 | N113: 0 | O113: FUNDACION VALLE DEL LILI | P113: =VLOOKUP(B113,'NIVEL ENERO'!A:D,3,0) -> 0.1162072 | Q113: =VLOOKUP(B113,'NIVEL ENERO'!A:D,4,0) -> 1244330.8 | R113: =+PROPER(C113&" "&D113) -> Popo Carabali Luz Dely | S113: =+YEARFRAC(L113,$S$1) -> 3.4166667 | T113: =+YEARFRAC(M113,$S$1) -> 5.6138889 | U113: =+$I113 -> 116826 | V113: =+PROPER(F113) -> Union Libre
B114: 25338294 | C114: PAZ MOSQUERA | D114: ILSA GEOVANA | E114: CALI | F114: Soltero(a) | G114: 1670000 | H114: 1121761 | J114: 46 | K114: 3 | L114: 45118 | M114: 41944 | N114: 0 | O114: FUNDACION VALLE DEL LILI | P114: =VLOOKUP(B114,'NIVEL ENERO'!A:D,3,0) -> 0.38115497 | Q114: =VLOOKUP(B114,'NIVEL ENERO'!A:D,4,0) -> 176392.33 | R114: =+PROPER(C114&" "&D114) -> Paz Mosquera Ilsa Geovana | S114: =+YEARFRAC(L114,$S$1) -> 2.8361111 | T114: =+YEARFRAC(M114,$S$1) -> 11.530556 | U114: =+$I114 -> 0 | V114: =+PROPER(F114) -> Soltero(A)
B115: 25341987 | C115: VALENCIA COBO | D115: ELIANA | E115: CALI | F115: Soltero(a) | G115: 1717900 | H115: 1500275 | I115: 0 | J115: 40 | K115: 2 | L115: 45220 | M115: 44683 | N115: 0 | O115: FUNDACION VALLE DEL LILI | P115: =VLOOKUP(B115,'NIVEL ENERO'!A:D,3,0) -> 0.4311341 | Q115: =VLOOKUP(B115,'NIVEL ENERO'!A:D,4,0) -> -22231.98 | R115: =+PROPER(C115&" "&D115) -> Valencia Cobo Eliana | S115: =+YEARFRAC(L115,$S$1) -> 2.5583333 | T115: =+YEARFRAC(M115,$S$1) -> 4.0277778 | U115: =+$I115 -> 0 | V115: =+PROPER(F115) -> Soltero(A)
B116: 25364521 | C116: GUERRERO FAJARDO | D116: GLORIA PIEDAD | E116: CALI | F116: Separado(a) | G116: 5842800 | H116: 10908857 | I116: 11051880 | J116: 53 | K116: 1 | L116: 41009 | M116: 35560 | N116: 5 | O116: FUNDACION VALLE DEL LILI | P116: =VLOOKUP(B116,'NIVEL ENERO'!A:D,3,0) -> 0.38987027 | Q116: =VLOOKUP(B116,'NIVEL ENERO'!A:D,4,0) -> 176042 | R116: =+PROPER(C116&" "&D116) -> Guerrero Fajardo Gloria Piedad | S116: =+YEARFRAC(L116,$S$1) -> 14.088889 | T116: =+YEARFRAC(M116,$S$1) -> 29.005556 | U116: =+$I116 -> 11051880 | V116: =+PROPER(F116) -> Separado(A)
B117: 25454154 | C117: PENNA OIDOR | D117: MARIA ISABEL | E117: CALOTO | F117: Casado(a) | G117: 2893800 | H117: 1355255 | I117: 1366269 | J117: 47 | K117: 1 | L117: 39569 | M117: 40674 | N117: 0 | O117: FUNDACION VALLE DEL LILI | P117: =VLOOKUP(B117,'NIVEL ENERO'!A:D,3,0) -> 0.42627098 | Q117: =VLOOKUP(B117,'NIVEL ENERO'!A:D,4,0) -> -24526 | R117: =+PROPER(C117&" "&D117) -> Penna Oidor Maria Isabel | S117: =+YEARFRAC(L117,$S$1) -> 18.030556 | T117: =+YEARFRAC(M117,$S$1) -> 15.002778 | U117: =+$I117 -> 1366269 | V117: =+PROPER(F117) -> Casado(A)
B118: 25601528 | C118: RODRIGUEZ MOSQUERA | D118: MANLY | E118: CALI | F118: Soltero(a) | G118: 2893800 | H118: 1557164 | J118: 53 | K118: 1 | L118: 44848 | M118: 44105 | N118: 0 | O118: FUNDACION VALLE DEL LILI | P118: =VLOOKUP(B118,'NIVEL ENERO'!A:D,3,0) -> 0.45437721 | Q118: =VLOOKUP(B118,'NIVEL ENERO'!A:D,4,0) -> -115752 | R118: =+PROPER(C118&" "&D118) -> Rodriguez Mosquera Manly | S118: =+YEARFRAC(L118,$S$1) -> 3.5777778 | T118: =+YEARFRAC(M118,$S$1) -> 5.6138889 | U118: =+$I118 -> 0 | V118: =+PROPER(F118) -> Soltero(A)
B119: 25733400 | C119: CICLOS LARGO | D119: LEYDA | E119: CALI | F119: Soltero(a) | G119: 2893800 | H119: 3542522 | I119: 1440591 | J119: 46 | K119: 1 | L119: 43395 | M119: 41654 | N119: 2 | O119: FUNDACION VALLE DEL LILI | P119: =VLOOKUP(B119,'NIVEL ENERO'!A:D,3,0) -> 0.37015125 | Q119: =VLOOKUP(B119,'NIVEL ENERO'!A:D,4,0) -> 185521.04 | R119: =+PROPER(C119&" "&D119) -> Ciclos Largo Leyda | S119: =+YEARFRAC(L119,$S$1) -> 7.5555556 | T119: =+YEARFRAC(M119,$S$1) -> 12.325 | U119: =+$I119 -> 1440591 | V119: =+PROPER(F119) -> Soltero(A)
B120: 26366473 | C120: LOPEZ MARTINEZ | D120: JAZMIN LUISA | E120: CALI | F120: Soltero(a) | G120: 2800000 | H120: 16892842 | I120: 16857937 | J120: 60 | K120: 2 | L120: 39342 | M120: 32568 | N120: 3 | O120: ADMINISTRADOR COLOMBIANA DE PENSIONES | P120: =VLOOKUP(B120,'NIVEL ENERO'!A:D,3,0) -> #N/A | Q120: =VLOOKUP(B120,'NIVEL ENERO'!A:D,4,0) -> #N/A | R120: =+PROPER(C120&" "&D120) -> Lopez Martinez Jazmin Luisa | S120: =+YEARFRAC(L120,$S$1) -> 18.652778 | T120: =+YEARFRAC(M120,$S$1) -> 37.197222 | U120: =+$I120 -> 16857937 | V120: =+PROPER(F120) -> Soltero(A)
B121: 27456572 | C121: QUENORAN POLINDARA | D121: SANDRA MILENA | E121: CALI | F121: Soltero(a) | G121: 2600900 | H121: 5722487 | I121: 0 | J121: 40 | K121: 2 | L121: 42930 | M121: 41774 | N121: 3 | O121: FUNDACION VALLE DEL LILI | P121: =VLOOKUP(B121,'NIVEL ENERO'!A:D,3,0) -> 0.15236764 | Q121: =VLOOKUP(B121,'NIVEL ENERO'!A:D,4,0) -> 696085 | R121: =+PROPER(C121&" "&D121) -> Quenoran Polindara Sandra Milena | S121: =+YEARFRAC(L121,$S$1) -> 8.8277778 | T121: =+YEARFRAC(M121,$S$1) -> 11.991667 | U121: =+$I121 -> 0 | V121: =+PROPER(F121) -> Soltero(A)
B122: 28540251 | C122: NAVAS JIMENEZ | D122: CLARA LUCIA | E122: CALI | F122: Casado(a) | G122: 10000000 | H122: 700000 | J122: 41 | K122: 2 | L122: 45352 | M122: 45000 | N122: 0 | O122: FUNDACION VALLE DEL LILI - HONORARIOS | P122: =VLOOKUP(B122,'NIVEL ENERO'!A:D,3,0) -> #N/A | Q122: =VLOOKUP(B122,'NIVEL ENERO'!A:D,4,0) -> #N/A | R122: =+PROPER(C122&" "&D122) -> Navas Jimenez Clara Lucia | S122: =+YEARFRAC(L122,$S$1) -> 2.1972222 | T122: =+YEARFRAC(M122,$S$1) -> 3.1583333 | U122: =+$I122 -> 0 | V122: =+PROPER(F122) -> Casado(A)
...

Sheet Capacidad_Endeudamiento
A1: cedula | B1: COOPERATIVA DE TRABAJADORES DE LA FUNDACIÓN VALLE DEL LILI | O1: =+IF(Datos_Iniciales!C8=2,(Capacidad_Endeudamiento!$C$25*Parametros!$H$5),Capacidad_Endeudamiento!$C$25) -> 2500000
B2: MODELO ASIGNACIÓN DE CRÉDITOS | O2: =IF($C$25>Parametros!$G$9,Parametros!$H$9,Parametros!$H$4) -> 0.08 | V2: N° CEDULA | W2: ASOCIADO | X2: EMPRESA | Y2: SALARIO | Z2: LÍNEA DE CRÉDITO | AA2: MONTO SOLICITADO | AB2: SCOR CIFIN | AC2: ENDEUDAMIENTO ACTUAL | AD2: ENDEUDAMIENTO PROYECTADO | AE2: CME | AF2: CMD | AG2: PERFIL | AH2: SOLVENCIA | AI2: NIVEL_EDEUDAMIENTO | AJ2: TASA | AK2: GARANTIA | AL2: DEUDA SECTOR | AM2: OBSERVACIONES | AN2: FECHA
B3: =+TODAY() -> 46154 | C3: Solicitud N° | V3: =+$C$11 -> 1112878165 | W3: =+$C$12 -> Varon Barrios Yina Marcela | X3: =+$C$13 -> FUNDACION VALLE DEL LILI | Y3: =+$C$25 -> 2500000 | Z3: =+$C$60 -> Cred.Ord. Gerencia | AA3: =+$C$61 -> 4000000 | AB3: =+$C$31 -> 657 | AC3: =+$C$84 -> 0.26 | AD3: =+$C$86 -> 0.35 | AE3: =+#REF! -> #REF! | AF3: =+$C$7 -> 0.35 | AG3: =+$C$5 -> C | AH3: =+$C$93 -> 0.39843807 | AI3: =+#REF! -> #REF! | AJ3: =+$C$64 -> 0.011040394 | AK3: =+$C$8 -> Aportes | AL3: =+$C$17 -> 0 | AM3: =+$B$114 -> 0 | AN3: =+NOW() -> 46154.724
B5: PERFIL | C5: =+'Base Perfil'!$V$4 -> C | D5: Calculo Motor | O5: =+$C$25-($O$2*$O$1) -> 2300000
B6: VALOR DESPROTEGIDO MAX DE LA LINEA | C6: =+IF(Datos_Iniciales!$C$4=1,IF($C$5=Parametros!$B$40,Parametros!$D$40,IF($C$5=Parametros!$B$41,Parametros!$D$41)),IF(AND($C$5=Parametros!$D$28,$C$37>=Parametros!$B$28,$C$37<=Parametros!$C$28),Parametros!$F$28,IF(AND($C$5=Parametros!$D$29,$C$37>=Parametros!$B$29,$C$37<=Parametros!$C$29),Parametros!$F$29,IF(AND($C$5=Parametros!$D$30,$C$37>=Parametros!$B$30,$C$37<=Parametros!$C$30),Parametros!$F$30,IF(AND($C$5=Parametros!$D$31,$C$37>=Parametros!$B$31,$C$37<=Parametros!$C$31),Parametros!$F$31,IF(AND($C$5=Parametros!$D$32,$C$37>=Parametros!$B$32,$C$37<=Parametros!$C$32),Parametros!$F$32,IF(AND($C$5=Parametros!$D$33,$C$37>=Parametros!$B$33,$C$37<=Parametros!$C$33),Parametros!$F$33,IF(AND($C$5=Parametros!$D$34,$C$37>=Parametros!$B$34),Parametros!$F$34,IF(AND($C$5=Parametros!$D$35,$C$37>=Parametros!$B$35),Parametros!$F$35,IF(AND($C$5=Parametros!$D$36,$C$37>=Parametros!$B$36),Parametros!$F$36,"N/A")))))))))) -> 3501810 | D6: Calculo Motor
B7: =+$O$7&" "&$O$9 -> VIABLE CMD | C7: =+IFERROR(MROUND(($C$75+$C$28-C20)/$O$5,1%),"") -> 0.35 | D7: Calculo Motor | O7: =+IF(C7>51%,"NO VIABLE","VIABLE") -> VIABLE | V7: Nota: | W7: =+IF($C$8="","FALTA "&$B$8,IF($C$64="","FALTA TASA DE INTERES",""))
B8: GARANTÍA | C8: Aportes | D8: Parámetro | L8: Credito | M8: =+VLOOKUP(Datos_Iniciales!$E$13,Datos_Iniciales!$Q$10:$R$12,2,FALSE()) -> Mensual
L9: Monto | M9: =+$C$61 -> 4000000 | O9: CMD
L10: Intereses Anual | M10: =+$C$64*12 -> 0.13248473
B11: N° Cedula | C11: 1112878165 | L11: Tiempo en Años | M11: =+$C$30 -> 1
A12: "primer_apellido"&"segundo_apellido": "BARRIOS"&"nombre": "YINA MARCELA", | B12: Asociado | C12: =+INDEX(Base_Asociados!$B$6:$V$9877,MATCH($C$11,Base_Asociados!$B$6:$B$9877,0),MATCH($B12,Base_Asociados!$B$5:$V$5,0)) -> Varon Barrios Yina Marcela | D12: API | L12: Pagos Anuales | M12: =+IF(Datos_Iniciales!$E$13=1,Datos_Iniciales!$S$10,IF(Datos_Iniciales!$E$13=2,Datos_Iniciales!$S$11,Datos_Iniciales!$S$12)) -> 12
A13: cliente_empresa | B13: Empresa | C13: =+INDEX(Base_Asociados!$B$6:$V$9877,MATCH($C$11,Base_Asociados!$B$6:$B$9877,0),MATCH($B13,Base_Asociados!$B$5:$V$5,0)) -> FUNDACION VALLE DEL LILI | D13: API | L13: Cuota | M13: =-PMT(M10/M12,M11*M12,M9) -> 357735.57
A14: saldo_fecha | B14: Aportes | C14: 3500000 | D14: API | L14: Cuota_Frecuencia | M14: =+IF(M8="Semanal",($M$13*$M$12)/12,IF(M8="Quincenal",M13*2,M13)) -> 357735.57
A15: SaldoCapital | B15: Deuda Coopvalili | C15: 2500671 | D15: API
B16: Cupo Rotativo
A17: Deuda <> TC y Coopvalili | B17: Deuda Sector | C17: 0 | D17: TU
A18: Deuda de tarjetas en TU | B18: Cupos TDC | C18: 4258000 | D18: TU | O18: SI
B19: Cuota TDC | C19: =+Datos_Iniciales!$E$18 -> 181631.4 | D19: Calculo Motor | O19: NO
A20: Cuota_fecha + ValorCuotaFija | B20: Cuota que Recoge Coopvalili | D20: API
B21: Cuota que Recoge Sector | D21: TU
O22: Normal
C24: =+Datos_Iniciales!$C$8 -> 1 | O24: Integral
B25: Salario | C25: 2500000 | D25: Chat | E25: No se si es Chat o Base_Asociados | O25: Pensionado
B26: Otros Ingresos | D26: No aplica
B27: Descuentos de Ley | C27: =+IF(AND($C$24=1,$C$25>Parametros!$G$9),$C$25*Parametros!$H$9,IF(AND($C$24=1,$C$25<=Parametros!$G$9),$C$25*Parametros!$H$4,IF(AND($C$24=2,$C$25>Parametros!$G$9),($C$25*Parametros!$H$5)*Parametros!$H$9,IF(AND($C$24=2,$C$25<=Parametros!$G$9),($C$25*Parametros!$H$5)*Parametros!$H$4,IF($C$24=3,$C$25*Parametros!$H$6))))) -> 200000 | D27: Cálculo Motor
B28: Egresos Volante de Pago | C28: 600000 | D28: Chat | E28: No se si es Chat o Base_Asociados
B29: Egresos Cuotas Sector | C29: 0 | D29: TU
B30: Plazo | C30: 1 | D30: No aplica
B31: Scor Cifin | C31: 657 | D31: TU
B32: Tasa Interés Efectiva | C32: 0.3015 | D32: Parámetro
A33: frecuencia | B33: Frecuencia de Pagos | C33: quincenal | D33: Chat
A34: frecuencia_mes | B34: Frecuencia mes | C34: =IF(C33="semanal",4,IF(C33="quincenal",2,IF(C33="mensual",1,"Revisar"))) -> 2 | D34: Cálculo Motor
B37: Ingresos | C37: =+$C$25 -> 2500000 | D37: Cálculo Motor | E37: Este cálculo implicitamente es mensual
B38: Mínimo Vital | C38: =+IF(AND(C25>=Parametros!$B$5,C25<=Parametros!$C$5),$C$25*Parametros!$D$5,IF(AND(C25>Parametros!$C$5,C25<=Parametros!$C$6),$C$25*Parametros!$D$6,IF(C25>Parametros!$C$7,$C$25*Parametros!D7))) -> 1250000 | D38: Cálculo Motor
B39: Egresos | C39: =+($C$28+$C$29+C19-C20-C21)-($C$26/2) -> 781631.4 | D39: Cálculo Motor
A40: cuota_max_deu_mes | B40: Cuota Máximo por Endeudamiento Mensual | C40: =+C25*0.5-C28 -> 650000 | D40: Cálculo Motor | E40: Este cálculo implicitamente es mensual
A41: cuota_max_deu_frec | B41: Cuota Máximo por Endeudamiento Periódica | C41: =+C40/C34 -> 325000 | D41: Cálculo Motor
A42: cuota_max_cap_mes | B42: Cuota Máxima por Capacidad Mensual | C42: =IF((C37-C38-C39)<0,0,(C37-C38-C39)) -> 468368.6 | D42: Cálculo Motor | E42: Este cálculo implicitamente es mensual
A43: cuota_max_cap_frec | B43: Cuota Máxima por Capacidad Periódica | C43: =+C42/C34 -> 234184.3 | D43: Cálculo Motor
A44: cuota_max_fin | B44: Cuota Máxima por Capacidad | C44: =MIN(C43,C41) -> 234184.3 | D44: Cálculo Motor
A45: monto_endeuda | B45: Maximo Deuda por Endeudamiento | C45: =IF(C44<=0,"Revisar",IFERROR(FLOOR($C$44*((1-(1+$C$64)^-$C$63)/$C$64),100000),0)) -> 4900000 | D45: Cálculo Motor
B49: Aportes y Ahorros | C49: =+$C$14+Datos_Iniciales!$C$25 -> 3500000 | D49: API
B50: Prenda 50% | C50: 0 | D50: No aplica
B51: Cesantias | C51: 0 | D51: No aplica
B52: Total Ahorros+Prestaciones | C52: =SUM(C49:C51) -> 3500000 | D52: Cálculo Motor
A53: monto_desprote | B53: Maximo Deuda por Desprotegido | C53: =FLOOR(C52+C6-C15,100000) -> 4500000 | D53: Cálculo Motor | E53: Nuevo Crédito = Total Aportes_Prest + Desprotegido viable - Deuda Actual
A55: monto_motor | B55: Valor Final del Crédito por Motor | C55: =MIN(C45,C53) -> 4500000 | D55: Cálculo Motor
C56: =+IF(C45="Revisar","OJO revisar CME",IF(C45<C61,"OJO revisar CME",""))
B60: Línea de crédito | C60: =+VLOOKUP(Datos_Iniciales!$C$6,'Lineas de Credito'!$A$5:$C$238,3,FALSE()) -> Cred.Ord. Gerencia | D60: Chat
A61: monto_solicitud | B61: Monto Solicitado | C61: 4000000 | D61: Chat
A62: tasa_namv | B62: Tasa de Interés Periódica | C62: =+NOMINAL(C32,C63) -> 0.26496945 | D62: Cálculo Motor
A63: periodos | B63: N° de Periodos (n) | C63: =IF(C33="Mensual",12,IF(C33="Quincenal",24,IF(C33="Semanal",52,""))) -> 24 | D63: Cálculo Motor
A64: tasa_per | B64: Tasa de Interés Periódica | C64: =+C62/C63 -> 0.011040394 | D64: Cálculo Motor
A65: cuota_Per_soli | B65: Cuota Periodica Solicitada | C65: =PMT(C64,C63,-C61) -> 190634.46 | D65: Cálculo Motor
A67: param | B67: Parámetro de crédito según reglas | C67: 2000000 | D67: Parámetro
A69: regla_1 | B69: Regla 1 monto_motor > = monto_solicitud | C69: =IF(C55>=C61,1,0) -> 1 | D69: Cálculo Motor | E69: 1 = Aplica 0= No aplica
A70: regla_2 | B70: Regla 2 monto_motor > = param | C70: =IF(AND(C55>=C67,C69=0),1,0) -> 0 | D70: Cálculo Motor | E70: 1 = Aplica 0= No aplica
A71: regla_3 | B71: Regla 3 param > = monto_motor | C71: =IF(AND(C67>C55,C69=0,C70=0),1,0) -> 0 | D71: Cálculo Motor | E71: 1 = Aplica 0= No aplica
A74: monto_def | B74: Monto definitivo | C74: =IF(C69=1,C55,IF(C70=1,C55, IF(C71=1,0,"Revisar") )) -> 4500000 | D74: Cálculo Motor
A75: cuota_def | B75: Cuota definitiva | C75: =PMT(C64,C63,-C74) -> 214463.77 | D75: Cálculo Motor
A76: concepto | B76: Concepto definitivo | C76: =IF(C69=1,"Preaprobado",IF(C70=1,"Preaprobado", IF(C71=1,"No viable","Revisar") )) -> Preaprobado | D76: Cálculo Motor
B83: Validación Endeudamiento
A84: end_actual | B84: Endeudamiento Actual | C84: =+IFERROR(MROUND(($C$28)/$O$5,1%),"") -> 0.26 | D84: Cálculo Motor
A85: end_actual_cupo | B85: Endeudamiento Actual con Cupo Coopvalili | C85: =+IFERROR(MROUND(($C$28+$C$16)/$O$5,1%),"") -> 0.26 | D85: Cálculo Motor
A86: end_proy | B86: Endeudamiento Proyectado | C86: =+IFERROR(MROUND(($C$28+$C$75-C20)/$O$5,1%),"") -> 0.35 | D86: Cálculo Motor
A87: end_proy_cupo | B87: Endeudamiento Proyectado Con Cupo Coopvalili | C87: =+IFERROR(MROUND(($C$28+$C$75+$C$16-C20)/$O$5,1%),"") -> 0.35 | D87: Cálculo Motor
A88: max_end | B88: Máximo Endeudamiento | C88: 0.5 | D88: Cálculo Motor
A89: cumple_end | B89: Cumple Endeudamiento | C89: =IF(C86<=C88,1,0) -> 1 | D89: Cálculo Motor | E89: 1 = Cumple 0= No cumple
B90: Cuota Disponible FVL | C90: =+IFERROR(INDEX(Base_Asociados!$B$6:$V$9877,MATCH($C$11,Base_Asociados!$B$6:$B$9877,0),MATCH($B90,Base_Asociados!$B$5:$V$5,0)),0) -> 267259.04 | D90: No aplica
B92: Validación Solvencia
A93: solvencia | B93: Solvencia | C93: =+IFERROR((C39+C75)/($C$25),"") -> 0.39843807 | D93: Cálculo Motor
A94: cumple_sol | B94: Cumple Endeudamiento | C94: =+IF(C93<=1,1,0) -> 1 | D94: Cálculo Motor | E94: 1 = Cumple 0= No cumple
B96: Validación Disponible
A97: disponible | B97: Disponible | C97: =+C37-C38-C39-C75 -> 253904.83 | D97: Cálculo Motor
A98: cumple_disp | B98: Cumple Endeudamiento | C98: =+IF(C97>10000,1,0) -> 1 | D98: Cálculo Motor | E98: 1 = Cumple 0= No cumple
B100: Validación Desprotegido
A101: max_desproteg | B101: Desprotegido Máximo | C101: =+C6 -> 3501810 | D101: Cálculo Motor
A102: desproteg | B102: Desprotegido | C102: =-C52+C74+C15 -> 3500671 | D102: Cálculo Motor
A103: cumple_sol | B103: Cumple Endeudamiento | C103: =IF(C102<=C101,1,0) -> 1 | D103: Cálculo Motor | E103: 1 = Cumple 0= No cumple
B105: Validación Cumplimiento
A106: cumple_total | B106: Cumplimiento 4 criterios | C106: =IF(C89+C94+C98+C103=4,1,0) -> 1 | D106: Cálculo Motor | E106: 1 = Cumple 0= No cumple
B109: Instancia de Aprobación | C109: Gerencia | D109: Parámetro
B113: Observaciones:
B118: Lorena Jimenez | C118: Hugo Fernando Dávila | D118: Modelo Realizado por : HFDL
B119: Realizo. | C119: Reviso.
B124: =+CONCATENATE("Historico Nivel de Endeudamiento"," - ",$C$12) -> Historico Nivel de Endeudamiento - Varon Barrios Yina Marcela
E129: Formulación
E130: 2021 | F130: 2022 | G130: 2023 | H130: 2024
E131: =+INDEX('Evaluacion de Cartera'!$B$3:$D$894,MATCH(Capacidad_Endeudamiento!$C$11,'Evaluacion de Cartera'!$B$3:$B$894,0),MATCH(Capacidad_Endeudamiento!E$130,'Evaluacion de Cartera'!$B$2:$D$2,0)) -> #N/A | F131: =+INDEX('Evaluacion de Cartera'!$B$3:$D$894,MATCH(Capacidad_Endeudamiento!$C$11,'Evaluacion de Cartera'!$B$3:$B$894,0),MATCH(Capacidad_Endeudamiento!F$130,'Evaluacion de Cartera'!$B$2:$D$2,0)) -> #N/A | G131: =+INDEX('Evaluacion de Cartera'!$B$3:$E$894,MATCH(Capacidad_Endeudamiento!$C$11,'Evaluacion de Cartera'!$B$3:$B$894,0),MATCH(Capacidad_Endeudamiento!G$130,'Evaluacion de Cartera'!$B$2:$E$2,0)) -> #N/A | H131: =+#REF! -> #REF!

Sheet Datos_Iniciales
B1: COOPVALILI
B2: MODELO ASIGNACION DE CREDITOS
B4: Crédito Afianzado | C4: 2
B6: Linea de Credito | C6: 19
B8: Tipo de Salario Asociado | C8: 1
B10: N° Cedula | C10: 1112878165 | Q10: 1 | R10: Semanal | S10: 52
B11: Salario | C11: =+INDEX(Base_Asociados!$B$6:$V$9877,MATCH(Datos_Iniciales!$C$10,Base_Asociados!$B$6:$B$9877,0),MATCH(Datos_Iniciales!$B11,Base_Asociados!$B$5:$V$5,0)) -> 1625000 | Q11: 2 | R11: Quincenal | S11: 24
B12: Otros Ingresos | Q12: 3 | R12: Mensual | S12: 12
B13: Egresos Volante de Pago | C13: 476010 | E13: 3
B14: Egresos Cuotas Sector | C14: 0
B15: Plazo en años | C15: 1
B16: Score Cifin | C16: =+VLOOKUP($C$10,Score_Cifin!$B$2:$C$1985,2,FALSE()) -> 657 | F16: 1
B17: Monto Solicitado | C17: 1400000 | E17: Cuota Cupo Tarjetas
B18: Cupos Tarjetas | C18: 4258000 | E18: =IF($F$16=1,-PMT(Parametros!$D$9,Parametros!D10,Datos_Iniciales!$C$18),0) -> 181631.4
B19: Aportes | C19: 1355255
B20: Deuda Coopvalili | C20: 2500671
B21: Deuda Sector | C21: 0
B22: Recoge Cuotas Coopvalili
B23: Recoge Cuotas Sector
B24: Cupo Rotativo Coopvalili
B25: Ahorros En El Fondo
B26: Usuario De Credito en Coopvalili | C26: 2592933
B27: Edad | C27: =+INDEX(Base_Asociados!$B$6:$V$9877,MATCH(Datos_Iniciales!$C$10,Base_Asociados!$B$6:$B$9877,0),MATCH(Datos_Iniciales!$B27,Base_Asociados!$B$5:$V$5,0)) -> 38
B28: Personas a Cargo | C28: =+INDEX(Base_Asociados!$B$6:$V$9877,MATCH(Datos_Iniciales!$C$10,Base_Asociados!$B$6:$B$9877,0),MATCH(Datos_Iniciales!$B28,Base_Asociados!$B$5:$V$5,0)) -> 0
B29: Tipo Vivienda | C29: =+INDEX(Base_Asociados!$B$6:$V$9877,MATCH(Datos_Iniciales!$C$10,Base_Asociados!$B$6:$B$9877,0),MATCH(Datos_Iniciales!$B29,Base_Asociados!$B$5:$V$5,0)) -> 4
B30: Antigüedad en la Cooperativa | C30: =+INDEX(Base_Asociados!$B$6:$V$9877,MATCH(Datos_Iniciales!$C$10,Base_Asociados!$B$6:$B$9877,0),MATCH(Datos_Iniciales!$B30,Base_Asociados!$B$5:$V$5,0)) -> 3.1583333
B31: Antigüedad Laboral | C31: =+INDEX(Base_Asociados!$B$6:$V$9877,MATCH(Datos_Iniciales!$C$10,Base_Asociados!$B$6:$B$9877,0),MATCH(Datos_Iniciales!$B31,Base_Asociados!$B$5:$V$5,0)) -> 3.4083333
B33: Pasivos | C33: =+C13+C14+E18 -> 657641.4
B34: Prenda
B35: Cesantias
C54: =+(Datos_Iniciales!$C$20+Datos_Iniciales!$C$21) -> 2500671

Sheet Hoja1
D2: Monto | E2: 98000000
D3: plazo | E3: 96
D4: tasa | E4: 0.0135
D5: cuota | E5: =+PMT(E4,E3,-E2) -> 1827365.1
D7: cuota real | E7: 1867588 | F7: =+E7-E5 -> 40222.887
D8: tasa real | E8: =RATE(E3,E7,-E2) -> 0.014076689
F9: =+F7*E3 -> 3861397.2

Sheet NIVEL ENERO
A1: 4661060 | B1: MINA ROBERTO CARLOS | C1: 0.39337458 | D1: 88218.54 | E1: Principal
A2: 5824652 | B2: CARVAJAL JIMENEZ CARLOS ANDRES | C2: 0.48223088 | D2: -222943 | E2: Principal
A3: 6537914 | B3: DELGADO ALVAREZ ALEXIS | C3: 0.1642021 | D3: 2109156 | E3: Principal
A4: 10280915 | B4: TRUJILLO ARANGO GERMAN HUMBERTO | C4: 0.47565441 | D4: -1187939.9 | E4: Principal
A5: 10285994 | B5: CORREA GARCIA ORLANDO | C5: 0.17595909 | D5: 1861721.8 | E5: Principal
A6: 11320970 | B6: HERNANDEZ CHAVEZ CARLOS HOLMES | C6: 0.42754621 | D6: -56033.88 | E6: Principal
A7: 14465776 | B7: CANAMEJOY GARCIA JUAN PABLO | C7: 0.46233948 | D7: -188224.8 | E7: Principal
A8: 14590768 | B8: LLOREDA MEJIA LUIS FRANCISCO | C8: 0.26518277 | D8: 1231980.9 | E8: Principal
A9: 14608714 | B9: DIAZ MENESES DAVID ORLANDO | C9: 0.18836387 | D9: 1768999.1 | E9: Principal
A10: 14621610 | B10: MUÑOZ VALERO ALVARO | C10: 0.22452655 | D10: 930825 | E10: Limonar
A11: 14837964 | B11: NIÑO MOTATO HUGO FERNANDO | C11: 0.36386528 | D11: 223252.68 | E11: Principal
A12: 14839579 | B12: TROCHEZ DELGADO JHON JAIRO | C12: 0.10864498 | D12: 1497029.2 | E12: Limonar
... A127: 34516193 | B127: GUAZA MEJIA ZULEIMA | C127: 0.46171638 | D127: -148886.6 | E127: Principal
A128: 34516353 | B128: OTALORA PALOMINO ILIEANA | C128: 0 | D128: 0 | E128: Principal
A129: 34558931 | B129: SANCHEZ HURTADO MARIA YANETH | C129: 0.31439015 | D129: 226464.3 | E129: Principal
A130: 34564166 | B130: ERIRA CEBALLOS EDIT MARGOT | C130: 0.47497047 | D130: -167545.94 | E130: Principal
A131: 34564544 | B131: MOSQUERA ARTEAGA NILSA YAZMIN | C131: 0.42709252 | D131: -34542 | E131: Principal
A132: 34615367 | B132: BOLAÑOS PAZ LEIDY JOHANNA | C132: 0.40885663 | D132: 101646.38 | E132: Principal
A133: 36175046 | B133: ALMARIO PERDOMO AMPARO | C133: 0.17543707 | D133: 1817304.1 | E133: Principal
A134: 38287868 | B134: TRIANA TRIVIÑO MARTHA ISABEL | C134: 0.14807781 | D134: 1120973.9 | E134: Principal
A135: 38462107 | B135: ORREGO FLOREZ MARLY SULEYDI | C135: 0.2973352 | D135: 872711 | E135: Principal
A136: 38556029 | B136: LOMBANA ESPINOSA CHARLENE ALEJANDRA | C136: 0.30426223 | D136: 950692.48 | E136: Principal
A137: 38557635 | B137: ANACONA HERNANDEZ YOLANDA LIRIA | C137: 0.53185456 | D137: -499894 | E137: Principal
A138: 38558372 | B138: OREJUELA GONZALEZ YOHANA | C138: 0.43525931 | D138: -59410.88 | E138: Principal
A139: 38559970 | B139: CORREA MUÑOZ LINDELIA | C139: 0.41803049 | D139: 6161.84 | E139: Principal
A140: 38560478 | B140: BONILLA VARGAS MARIA DEL PILAR | C140: 0.16654109 | D140: 2534437 | E140: Principal
... A166: 52026283 | B166: MURILLO ANZOLA ANGELA MARIA | C166: 0.27175196 | D166: 565041.62 | E166: Principal
A167: 52316905 | B167: GIL AMPUDIA CAROLINA | C167: 0 | D167: 0 | E167: Principal
A168: 55113244 | B168: DIAZ MONTEALEGRE SILVIA LORENA | C168: 0.12470916 | D168: 1911831 | E168: Principal
A169: 59666004 | B169: CASTILLO VALENTIERRA CARMEN MANUELA | C169: 0.16813129 | D169: 1226651 | E169: Principal
A170: 59801808 | B170: TREJO ROJAS DAYRA YAMILE | C170: 0.30446083 | D170: 391679.98 | E170: Limonar
A171: 59816941 | B171: VASQUEZ MUÑOZ DALY RIGUEY | C171: 0.20556673 | D171: 1161971 | E171: Principal
A172: 60328704 | B172: GOMEZ HERNANDEZ MARIA ELVIRA | C172: 0.40611388 | D172: 28792.24 | E172: Principal
A173: 60337190 | B173: PATIÑO BETANCOURT ANA JOSEFA | C173: 0.23162067 | D173: 1172699 | E173: Principal
A174: 60406095 | B174: PRATO HERNANDEZ ROSA MARGARITA | C174: 0.42961251 | D174: -56164 | E174: Limonar
A175: 66656138 | B175: MARTINEZ GUTIERREZ LUZBEIRA | C175: 0.50254482 | D175: -330105.48 | E175: Principal
A176: 66656378 | B176: CIFUENTES POSADA DORHIE ZULENY | C176: 0.26744638 | D176: 682292.08 | E176: Principal
A177: 66702591 | B177: LEON RIOS LILIANA | C177: 0.3193359 | D177: 453662.86 | E177: Principal
A178: 66718924 | B178: LOPEZ ARANA GISELA | C178: 0.42853835 | D178: -28986 | E178: Principal
A179: 66764802 | B179: ORTEGA ROJAS GLADYS | C179: 0.53298321 | D179: -352241.67 | E179: Principal
... A330: 38642747 | B330: GALLEGO PAZ SONIA YURANY | C330: 0.1525089 | D330: 1562897 | E330: Principal
A331: 1130585077 | B331: VIVAS MORENO SANDRA YAMILET | C331: 0 | D331: 0 | E331: Principal
A332: 14607266 | B332: RAMOS LASSO JULIAN | C332: 0.17074916 | D332: 1794590.1 | E332: Principal
A333: 1143934493 | B333: USECHE BECERRA BRIAN ALEXIS | C333: 0.36647981 | D333: 218667.92 | E333: Principal
A334: 1006165643 | B334: VALENCIA IPIALES JUAN PABLO | C334: 0.44164092 | D334: -90870.56 | E334: Principal
A335: 31974020 | B335: MOSQUERA MOSQUERA BEATRIZ | C335: 0.24845108 | D335: 639688.58 | E335: Principal
A336: 1151943115 | B336: GIRALDO SILVA JULIETH | C336: 0.11283441 | D336: 1625213.4 | E336: Alfaguara
A337: 34613050 | B337: ORTIZ NIÑO LUZ MARINA | C337: 0.34568386 | D337: 404867.12 | E337: Principal
A338: 38683545 | B338: ORDOÑEZ ORDOÑEZ DOLLY MARGOTH | C338: 0.43902662 | D338: -84109 | E338: Principal
A339: 67010687 | B339: VERA CORTES LIZETH PATRICIA | C339: 0.29391286 | D339: 414543 | E339: Principal
A340: 67004195 | B340: MONROY MARULANDA JENNY | C340: 0.39508522 | D340: 71924 | E340: Principal
A341: 66771259 | B341: REYES MADRIÑAN MARIA XIMENA | C341: 0.45793521 | D341: -75529 | E341: Principal
A342: 6391199 | B342: ANDRADE BLANCO LUIS FERNANDO | C342: 0.35000198 | D342: 276853.6 | E342: Principal
A343: 66899264 | B343: TREJOS APRAEZ YACKELINE | C343: 0.39020531 | D343: 77493 | E343: Principal
... A387: 67041989 | B387: AMEZQUITA RESTREPO YULY ANDREA | C387: 0.48303433 | D387: -163946 | E387: Principal
A388: 1144026406 | B388: BENAVIDES ZAPATA KELLY CAROLINA | C388: 0 | D388: 0 | E388: Principal
A389: 29545130 | B389: BENAVIDEZ RICO YENIFER | C389: 0.14025598 | D389: 949675 | E389: Principal
A390: 34674541 | B390: LOPEZ TOBAR FLORESNEIDA | C390: 0.40152977 | D390: 67089.04 | E390: Principal
A391: 1143844784 | B391: GARCIA JIMENEZ DIANA MARCELA | C391: 0.2905771 | D391: 374524 | E391: Limonar
A392: 16918740 | B392: CALLE CAMACHO DEYBI | C392: 0.12327269 | D392: 1036640.6 | E392: Principal
A393: 67000840 | B393: CLAVIJO MARGARITA | C393: 0.41647147 | D393: 14252.06 | E393: Principal
A394: 66873270 | B394: SALDARRIAGA ZULUAGA CAROLINA | C394: 0.46183332 | D394: -166833.26 | E394: Alfaguara
A395: 1144063930 | B395: MONTOYA MARTINEZ LORENA | C395: 0.12475227 | D395: 1002307 | E395: Principal
A396: 29508587 | B396: MACHADO ESCOBAR LUZ MARINA | C396: 0.42532189 | D396: -16706.34 | E396: Principal
A397: 1144170609 | B397: LOMBANA RODRIGUEZ DIANA CAROLINA | C397: 0.38701016 | D397: 95466 | E397: Principal
A398: 94556574 | B398: MIRAMAG MUÑOZ JUAN CARLOS | C398: 0.38763663 | D398: 96635.76 | E398: Limonar
A399: 31711815 | B399: DUQUE MENESES DIANA LORENA | C399: 0.22669306 | D399: 623351.66 | E399: Principal
A400: 1144167122 | B400: GONZALEZ HINCAPIE LEONARDO | C400: 0.32817594 | D400: 458485.8 | E400: Principal
... A505: 1114876803 | B505: LONDOÑO BARONA CAROLINA | C505: 0.31016664 | D505: 342032.8 | E505: Principal
A506: 1061435339 | B506: DIAZ VILLEGAS DANY FELIPE | C506: 0 | D506: 0 | E506: Principal
A507: 73432460 | B507: FALCON PEREZ PEDRO FABIAN | C507: 0.32698056 | D507: 1343200.1 | E507: Principal
A508: 1130608171 | B508: BRAVO CUYATO DIANA CAROLINA | C508: 0.34942674 | D508: 183554 | E508: Principal
A509: 1143838419 | B509: TAPASCO MARTINEZ NUR ELIZANA | C509: 0.11675686 | D509: 877525 | E509: Principal
A510: 1144126183 | B510: ROCHA GUTIERREZ CINDY YULIED | C510: 0.25222332 | D510: 589270.72 | E510: Limonar
A511: 1130679196 | B511: VALENCIA RUIZ BEATRIZ ELENA | C511: 0.38042832 | D511: 389996.84 | E511: Principal
A512: 1107066677 | B512: FLOR OTERO ANGIE YULIETH | C512: 0.40069944 | D512: 60044.8 | E512: Principal
A513: 31714200 | B513: BEDOYA CORTES OLGA LUCIA | C513: 0.36652326 | D513: 154751 | E513: Principal
A514: 1044423154 | B514: LEIVA HERNANDEZ JOAN MANUEL | C514: 0.36545282 | D514: 348085.94 | E514: Principal
A515: 38552196 | B515: VELEZ CASTILLO YOHANA PATRICIA | C515: 0.23749481 | D515: 659114.02 | E515: Principal
A516: 1144136654 | B516: CANTERO SOTO NATALIA | C516: 0.16347838 | D516: 1285985 | E516: Principal
A517: 1143848340 | B517: RINCON BURBANO KARENT YULIETH | C517: 0.22949419 | D517: 665937.2 | E517: Principal
A518: 31305334 | B518: CASTRO VALENCIA ANA MILENA | C518: 0.40068396 | D518: 53108.64 | E518: Principal
... A719: 1112479971 | B719: CALVO ELIANA FERNANDA | C719: 0.34991177 | D719: 320153 | E719: Principal
A720: 1107509624 | B720: AGUIRRE CARMONA KATHERINE | C720: 0 | D720: 0 | E720: Principal
A721: 31097169 | B721: CASTRO MARIN ANA MARIA | C721: 0.26246919 | D721: 920421 | E721: Principal
A722: 1144043829 | B722: MUÑOZ ROJAS LIZETH KARIME | C722: 0.31679171 | D722: 399694.98 | E722: Principal
A723: 1144031120 | B723: GOMEZ MORALES KATHERINE | C723: 0.32395689 | D723: 412057.26 | E723: Principal
A724: 1144155514 | B724: PALACIOS SIERRA YAIRA MILENA | C724: 0.40945373 | D724: 38630.28 | E724: Principal
A725: 1144067354 | B725: BAHAMON URIBE DANIELA | C725: 0.20098305 | D725: 1160435.4 | E725: Limonar
A726: 29352680 | B726: CAICEDO CAMPO DIANA CAROLINA | C726: 0.16133841 | D726: 1518360.4 | E726: Principal
A727: 31324094 | B727: FLOR DIAZ DIANA MARIA | C727: 0.41326332 | D727: 22395.04 | E727: Principal
A728: 1085293834 | B728: GUERRERO BOLAÑOS SARITA JULIE | C728: 0.16470928 | D728: 1208205.7 | E728: Limonar
A729: 1144054574 | B729: FIGUEROA SALCEDO JEFERSON | C729: 0.25464714 | D729: 1393164 | E729: Principal
A730: 1130675011 | B730: HIDALGO GOMEZ DIANA MARIA | C730: 0.47646067 | D730: -154297.4 | E730: Principal
A731: 1112479726 | B731: AVILA PIAMBA BRAHYAN MAURICIO | C731: 0.3179562 | D731: 323294.88 | E731: Limonar
A732: 1062290251 | B732: MEZU FIGUEROA VIVIAN LISET | C732: 0.21396517 | D732: 535876 | E732: Principal
... A743: 1144060563 | B743: RIVERA RODRIGUEZ JENNIFER | C743: 0.26559334 | D743: 446822 | E743: Limonar
A744: 1143860441 | B744: LLANTEN GRANDA DIANA MARCELA | C744: 0 | D744: 0 | E744: Principal
A745: 1234196269 | B745: GALINDEZ PIPICANO INGRITH CAMILA | C745: 0.1822016 | D745: 688141 | E745: Principal
A746: 1062324690 | B746: BALANTA GARCIA ALVARO JAVIER | C746: 0.3924808 | D746: 114110.16 | E746: Principal
...
